{
"meta":{"test_sets":[],"test_metrics":[],"learn_metrics":[{"best_value":"Min","name":"MultiClass"}],"launch_mode":"Train","parameters":"","iteration_count":1000,"learn_sets":["learn"],"name":"experiment"},
"iterations":[
{"learn":[2.509360315],"iteration":0,"passed_time":0.2480012961,"remaining_time":247.7532948},
{"learn":[2.222099707],"iteration":1,"passed_time":0.3122200933,"remaining_time":155.7978266},
{"learn":[1.938041396],"iteration":2,"passed_time":0.3755339719,"remaining_time":124.8024567},
{"learn":[1.744650745],"iteration":3,"passed_time":0.4392858474,"remaining_time":109.382176},
{"learn":[1.554019394],"iteration":4,"passed_time":0.5004441539,"remaining_time":99.58838663},
{"learn":[1.425008641],"iteration":5,"passed_time":0.5632131064,"remaining_time":93.30563796},
{"learn":[1.284567975],"iteration":6,"passed_time":0.6279095459,"remaining_time":89.07345415},
{"learn":[1.182210294],"iteration":7,"passed_time":0.6929054903,"remaining_time":85.92028079},
{"learn":[1.089544971],"iteration":8,"passed_time":0.7552769345,"remaining_time":83.16438245},
{"learn":[1.003509331],"iteration":9,"passed_time":0.8177509832,"remaining_time":80.95734734},
{"learn":[0.92933711],"iteration":10,"passed_time":0.8809545139,"remaining_time":79.20581947},
{"learn":[0.8641087533],"iteration":11,"passed_time":0.946091696,"remaining_time":77.89488297},
{"learn":[0.8061332222],"iteration":12,"passed_time":1.009033881,"remaining_time":76.60895699},
{"learn":[0.756017805],"iteration":13,"passed_time":1.072576611,"remaining_time":75.54003849},
{"learn":[0.7113947908],"iteration":14,"passed_time":1.138290674,"remaining_time":74.74775429},
{"learn":[0.668876685],"iteration":15,"passed_time":1.200916741,"remaining_time":73.85637955},
{"learn":[0.631139912],"iteration":16,"passed_time":1.266671718,"remaining_time":73.24342934},
{"learn":[0.594727502],"iteration":17,"passed_time":1.329011761,"remaining_time":72.50497494},
{"learn":[0.5638748462],"iteration":18,"passed_time":1.393171169,"remaining_time":71.9316272},
{"learn":[0.5309364416],"iteration":19,"passed_time":1.454668859,"remaining_time":71.27877409},
{"learn":[0.5036247999],"iteration":20,"passed_time":1.51611037,"remaining_time":70.67962156},
{"learn":[0.4773333906],"iteration":21,"passed_time":1.57783117,"remaining_time":70.14176746},
{"learn":[0.4539187869],"iteration":22,"passed_time":1.640476176,"remaining_time":69.68457494},
{"learn":[0.4319208455],"iteration":23,"passed_time":1.705707409,"remaining_time":69.36543464},
{"learn":[0.4121667884],"iteration":24,"passed_time":1.768449845,"remaining_time":68.96954396},
{"learn":[0.3916449021],"iteration":25,"passed_time":1.83180698,"remaining_time":68.62230765},
{"learn":[0.3747798942],"iteration":26,"passed_time":1.896840937,"remaining_time":68.35652711},
{"learn":[0.356315526],"iteration":27,"passed_time":1.960408354,"remaining_time":68.05417573},
{"learn":[0.3404999401],"iteration":28,"passed_time":2.02292691,"remaining_time":67.73317343},
{"learn":[0.3248312778],"iteration":29,"passed_time":2.086197182,"remaining_time":67.4537089},
{"learn":[0.3104387017],"iteration":30,"passed_time":2.149330002,"remaining_time":67.18389586},
{"learn":[0.2984612968],"iteration":31,"passed_time":2.211876217,"remaining_time":66.90925557},
{"learn":[0.2858555608],"iteration":32,"passed_time":2.280832339,"remaining_time":66.83529915},
{"learn":[0.2739679098],"iteration":33,"passed_time":2.349958398,"remaining_time":66.76646509},
{"learn":[0.2645258794],"iteration":34,"passed_time":2.410639246,"remaining_time":66.46476777},
{"learn":[0.2564017341],"iteration":35,"passed_time":2.47164927,"remaining_time":66.18527488},
{"learn":[0.2481975923],"iteration":36,"passed_time":2.534290214,"remaining_time":65.96003988},
{"learn":[0.2390907129],"iteration":37,"passed_time":2.599111227,"remaining_time":65.79855263},
{"learn":[0.2295862043],"iteration":38,"passed_time":2.662354072,"remaining_time":65.60313495},
{"learn":[0.2202570676],"iteration":39,"passed_time":2.7308524,"remaining_time":65.54045761},
{"learn":[0.2134226824],"iteration":40,"passed_time":2.79526624,"remaining_time":65.38195912},
{"learn":[0.2061482954],"iteration":41,"passed_time":2.859033683,"remaining_time":65.21319687},
{"learn":[0.1989736019],"iteration":42,"passed_time":2.922112732,"remaining_time":65.03399732},
{"learn":[0.1931794836],"iteration":43,"passed_time":2.985106226,"remaining_time":64.85821709},
{"learn":[0.1871427343],"iteration":44,"passed_time":3.04796251,"remaining_time":64.68453772},
{"learn":[0.1820252334],"iteration":45,"passed_time":3.111517917,"remaining_time":64.53017594},
{"learn":[0.1761739889],"iteration":46,"passed_time":3.173197236,"remaining_time":64.34163757},
{"learn":[0.1701459214],"iteration":47,"passed_time":3.235102593,"remaining_time":64.16286809},
{"learn":[0.1656544177],"iteration":48,"passed_time":3.297274625,"remaining_time":63.99404425},
{"learn":[0.1606535516],"iteration":49,"passed_time":3.357789021,"remaining_time":63.79799139},
{"learn":[0.1563257004],"iteration":50,"passed_time":3.423946551,"remaining_time":63.71226032},
{"learn":[0.1520350059],"iteration":51,"passed_time":3.489385132,"remaining_time":63.6141751},
{"learn":[0.1476220882],"iteration":52,"passed_time":3.545635964,"remaining_time":63.35315581},
{"learn":[0.1431695784],"iteration":53,"passed_time":3.600558416,"remaining_time":63.07644928},
{"learn":[0.1394042995],"iteration":54,"passed_time":3.658431806,"remaining_time":62.85851012},
{"learn":[0.1358388839],"iteration":55,"passed_time":3.716650105,"remaining_time":62.65210177},
{"learn":[0.1321630604],"iteration":56,"passed_time":3.781513136,"remaining_time":62.56082258},
{"learn":[0.1284635389],"iteration":57,"passed_time":3.84770937,"remaining_time":62.49210736},
{"learn":[0.1248607799],"iteration":58,"passed_time":3.908837958,"remaining_time":62.34265285},
{"learn":[0.121747749],"iteration":59,"passed_time":3.973767558,"remaining_time":62.25569174},
{"learn":[0.1184575151],"iteration":60,"passed_time":4.037991516,"remaining_time":62.15859072},
{"learn":[0.1156743206],"iteration":61,"passed_time":4.103689329,"remaining_time":62.08484823},
{"learn":[0.113154467],"iteration":62,"passed_time":4.167221564,"remaining_time":61.97915247},
{"learn":[0.1110051561],"iteration":63,"passed_time":4.232290759,"remaining_time":61.89725235},
{"learn":[0.108786433],"iteration":64,"passed_time":4.29874469,"remaining_time":61.83578901},
{"learn":[0.1064601605],"iteration":65,"passed_time":4.365302432,"remaining_time":61.77564351},
{"learn":[0.1043316903],"iteration":66,"passed_time":4.429918718,"remaining_time":61.68827111},
{"learn":[0.1015366858],"iteration":67,"passed_time":4.492926667,"remaining_time":61.57952431},
{"learn":[0.09928876515],"iteration":68,"passed_time":4.553956442,"remaining_time":61.44541228},
{"learn":[0.09755125882],"iteration":69,"passed_time":4.614857493,"remaining_time":61.31167812},
{"learn":[0.09557058486],"iteration":70,"passed_time":4.676859459,"remaining_time":61.19440053},
{"learn":[0.09375995781],"iteration":71,"passed_time":4.737960109,"remaining_time":61.06704141},
{"learn":[0.09209632735],"iteration":72,"passed_time":4.801064982,"remaining_time":60.96694847},
{"learn":[0.09067295003],"iteration":73,"passed_time":4.866603655,"remaining_time":60.89831061},
{"learn":[0.08877277473],"iteration":74,"passed_time":4.952835249,"remaining_time":61.08496807},
{"learn":[0.08661027404],"iteration":75,"passed_time":5.038188003,"remaining_time":61.2537594},
{"learn":[0.08502466201],"iteration":76,"passed_time":5.104263335,"remaining_time":61.18487089},
{"learn":[0.08368567997],"iteration":77,"passed_time":5.168344782,"remaining_time":61.09248576},
{"learn":[0.08224970254],"iteration":78,"passed_time":5.232608691,"remaining_time":61.00294436},
{"learn":[0.08050879795],"iteration":79,"passed_time":5.295901532,"remaining_time":60.90286762},
{"learn":[0.07943321616],"iteration":80,"passed_time":5.358970503,"remaining_time":60.80115916},
{"learn":[0.07824190118],"iteration":81,"passed_time":5.41886506,"remaining_time":60.66485519},
{"learn":[0.07670404153],"iteration":82,"passed_time":5.479109151,"remaining_time":60.53425412},
{"learn":[0.07496919832],"iteration":83,"passed_time":5.543111878,"remaining_time":60.44631524},
{"learn":[0.0737251863],"iteration":84,"passed_time":5.606501467,"remaining_time":60.35233932},
{"learn":[0.07254281674],"iteration":85,"passed_time":5.666629646,"remaining_time":60.22441275},
{"learn":[0.07141380685],"iteration":86,"passed_time":5.724588598,"remaining_time":60.07528035},
{"learn":[0.07049888478],"iteration":87,"passed_time":5.780857959,"remaining_time":59.91070976},
{"learn":[0.06944833484],"iteration":88,"passed_time":5.838006738,"remaining_time":59.75757458},
{"learn":[0.06832626869],"iteration":89,"passed_time":5.90205759,"remaining_time":59.67636008},
{"learn":[0.06756188371],"iteration":90,"passed_time":5.964123926,"remaining_time":59.57569943},
{"learn":[0.06655767384],"iteration":91,"passed_time":6.028543898,"remaining_time":59.49910717},
{"learn":[0.06524180432],"iteration":92,"passed_time":6.090933087,"remaining_time":59.40297108},
{"learn":[0.0644368739],"iteration":93,"passed_time":6.15182617,"remaining_time":59.29313309},
{"learn":[0.06350302577],"iteration":94,"passed_time":6.211040871,"remaining_time":59.16833671},
{"learn":[0.06274015666],"iteration":95,"passed_time":6.271086734,"remaining_time":59.05273341},
{"learn":[0.06178342452],"iteration":96,"passed_time":6.32909927,"remaining_time":58.91934681},
{"learn":[0.06094445182],"iteration":97,"passed_time":6.386370057,"remaining_time":58.78067134},
{"learn":[0.05991883184],"iteration":98,"passed_time":6.443813674,"remaining_time":58.64521334},
{"learn":[0.05925151915],"iteration":99,"passed_time":6.501045279,"remaining_time":58.50940752},
{"learn":[0.058208979],"iteration":100,"passed_time":6.558342913,"remaining_time":58.37574533},
{"learn":[0.05749023484],"iteration":101,"passed_time":6.61548513,"remaining_time":58.24221222},
{"learn":[0.05672496041],"iteration":102,"passed_time":6.673519615,"remaining_time":58.11793296},
{"learn":[0.05595001457],"iteration":103,"passed_time":6.732121376,"remaining_time":57.99981493},
{"learn":[0.05530274036],"iteration":104,"passed_time":6.791153848,"remaining_time":57.88650185},
{"learn":[0.05459944465],"iteration":105,"passed_time":6.852190013,"remaining_time":57.79111199},
{"learn":[0.05383996762],"iteration":106,"passed_time":6.915102108,"remaining_time":57.7120204},
{"learn":[0.05295936296],"iteration":107,"passed_time":6.97524574,"remaining_time":57.61036297},
{"learn":[0.05233486148],"iteration":108,"passed_time":7.038040032,"remaining_time":57.53113457},
{"learn":[0.05155106279],"iteration":109,"passed_time":7.102606622,"remaining_time":57.46654448},
{"learn":[0.05064153891],"iteration":110,"passed_time":7.164960745,"remaining_time":57.38423516},
{"learn":[0.05000182896],"iteration":111,"passed_time":7.228204551,"remaining_time":57.30933608},
{"learn":[0.04949669655],"iteration":112,"passed_time":7.289389463,"remaining_time":57.21848189},
{"learn":[0.04908348364],"iteration":113,"passed_time":7.351757459,"remaining_time":57.13734306},
{"learn":[0.04850243445],"iteration":114,"passed_time":7.414463828,"remaining_time":57.05913468},
{"learn":[0.04805400635],"iteration":115,"passed_time":7.475777803,"remaining_time":56.97058257},
{"learn":[0.0476431586],"iteration":116,"passed_time":7.536834733,"remaining_time":56.88055615},
{"learn":[0.0471845237],"iteration":117,"passed_time":7.599158694,"remaining_time":56.80049125},
{"learn":[0.04673096309],"iteration":118,"passed_time":7.661059035,"remaining_time":56.71758832},
{"learn":[0.04587260343],"iteration":119,"passed_time":7.721107053,"remaining_time":56.62145173},
{"learn":[0.04546205632],"iteration":120,"passed_time":7.783569359,"remaining_time":56.54345014},
{"learn":[0.04507851068],"iteration":121,"passed_time":7.846734717,"remaining_time":56.47076296},
{"learn":[0.0444799001],"iteration":122,"passed_time":7.911731883,"remaining_time":56.41129156},
{"learn":[0.04408661903],"iteration":123,"passed_time":7.972831841,"remaining_time":56.32419914},
{"learn":[0.04349294353],"iteration":124,"passed_time":8.035422874,"remaining_time":56.24796012},
{"learn":[0.043117796],"iteration":125,"passed_time":8.095859634,"remaining_time":56.1569946},
{"learn":[0.04274635035],"iteration":126,"passed_time":8.156903755,"remaining_time":56.07068487},
{"learn":[0.04250358812],"iteration":127,"passed_time":8.220020209,"remaining_time":55.99888768},
{"learn":[0.04205722165],"iteration":128,"passed_time":8.282268714,"remaining_time":55.92136473},
{"learn":[0.04150898981],"iteration":129,"passed_time":8.344809527,"remaining_time":55.84603299},
{"learn":[0.04107716456],"iteration":130,"passed_time":8.405216247,"remaining_time":55.75673984},
{"learn":[0.04070045305],"iteration":131,"passed_time":8.466823076,"remaining_time":55.67577598},
{"learn":[0.04040553072],"iteration":132,"passed_time":8.52872373,"remaining_time":55.5970186},
{"learn":[0.03998662581],"iteration":133,"passed_time":8.591354736,"remaining_time":55.52323284},
{"learn":[0.03939721907],"iteration":134,"passed_time":8.652728031,"remaining_time":55.44155368},
{"learn":[0.03895200699],"iteration":135,"passed_time":8.716004096,"remaining_time":55.37226132},
{"learn":[0.03862056258],"iteration":136,"passed_time":8.780855632,"remaining_time":55.3129811},
{"learn":[0.03820190932],"iteration":137,"passed_time":8.842815489,"remaining_time":55.23555762},
{"learn":[0.03760216011],"iteration":138,"passed_time":8.905744857,"remaining_time":55.16436203},
{"learn":[0.03722564865],"iteration":139,"passed_time":8.96792596,"remaining_time":55.08868804},
{"learn":[0.03695336242],"iteration":140,"passed_time":9.029519211,"remaining_time":55.00962413},
{"learn":[0.03663622351],"iteration":141,"passed_time":9.089692323,"remaining_time":54.92222544},
{"learn":[0.03634235117],"iteration":142,"passed_time":9.149650088,"remaining_time":54.83391696},
{"learn":[0.0360383156],"iteration":143,"passed_time":9.210506133,"remaining_time":54.75134201},
{"learn":[0.03581302498],"iteration":144,"passed_time":9.272409211,"remaining_time":54.67524052},
{"learn":[0.03545085113],"iteration":145,"passed_time":9.333564491,"remaining_time":54.59495942},
{"learn":[0.03510243458],"iteration":146,"passed_time":9.39583295,"remaining_time":54.521398},
{"learn":[0.03477336698],"iteration":147,"passed_time":9.456588581,"remaining_time":54.43928021},
{"learn":[0.03452114015],"iteration":148,"passed_time":9.517702058,"remaining_time":54.35949296},
{"learn":[0.03423316326],"iteration":149,"passed_time":9.579758464,"remaining_time":54.28529796},
{"learn":[0.0339577549],"iteration":150,"passed_time":9.635313148,"remaining_time":54.1747077},
{"learn":[0.03371232407],"iteration":151,"passed_time":9.695802855,"remaining_time":54.09237382},
{"learn":[0.03344157709],"iteration":152,"passed_time":9.7545976,"remaining_time":54.00094227},
{"learn":[0.03318760609],"iteration":153,"passed_time":9.814095054,"remaining_time":53.9137949},
{"learn":[0.03303350373],"iteration":154,"passed_time":9.873012934,"remaining_time":53.82384471},
{"learn":[0.03281759013],"iteration":155,"passed_time":9.934086625,"remaining_time":53.74595584},
{"learn":[0.03253978866],"iteration":156,"passed_time":9.993836085,"remaining_time":53.66117083},
{"learn":[0.03215987254],"iteration":157,"passed_time":10.0535821,"remaining_time":53.57668435},
{"learn":[0.03195827156],"iteration":158,"passed_time":10.11308791,"remaining_time":53.49123856},
{"learn":[0.03174782593],"iteration":159,"passed_time":10.17124233,"remaining_time":53.39902221},
{"learn":[0.03155695816],"iteration":160,"passed_time":10.22829708,"remaining_time":53.30149844},
{"learn":[0.03132701596],"iteration":161,"passed_time":10.28587059,"remaining_time":53.20715775},
{"learn":[0.03116778512],"iteration":162,"passed_time":10.34881934,"remaining_time":53.14086984},
{"learn":[0.03095594165],"iteration":163,"passed_time":10.40713422,"remaining_time":53.05100125},
{"learn":[0.03076971599],"iteration":164,"passed_time":10.46294582,"remaining_time":52.94884701},
{"learn":[0.0305702958],"iteration":165,"passed_time":10.51657849,"remaining_time":52.83630397},
{"learn":[0.03031007233],"iteration":166,"passed_time":10.570313,"remaining_time":52.72497445},
{"learn":[0.03013054041],"iteration":167,"passed_time":10.62326614,"remaining_time":52.61046089},
{"learn":[0.02994947965],"iteration":168,"passed_time":10.67729018,"remaining_time":52.50194166},
{"learn":[0.02975341477],"iteration":169,"passed_time":10.73419883,"remaining_time":52.40814724},
{"learn":[0.02955793918],"iteration":170,"passed_time":10.78943804,"remaining_time":52.30669085},
{"learn":[0.02940837156],"iteration":171,"passed_time":10.8478086,"remaining_time":52.22084605},
{"learn":[0.0292581504],"iteration":172,"passed_time":10.90519029,"remaining_time":52.13059175},
{"learn":[0.02910075251],"iteration":173,"passed_time":10.96214844,"remaining_time":52.03870465},
{"learn":[0.02895188328],"iteration":174,"passed_time":11.01817316,"remaining_time":51.94281632},
{"learn":[0.02870440893],"iteration":175,"passed_time":11.07452016,"remaining_time":51.84888983},
{"learn":[0.02844454148],"iteration":176,"passed_time":11.13022381,"remaining_time":51.75239659},
{"learn":[0.02825250709],"iteration":177,"passed_time":11.18964581,"remaining_time":51.67353291},
{"learn":[0.02811616666],"iteration":178,"passed_time":11.24469522,"remaining_time":51.57483114},
{"learn":[0.02786024835],"iteration":179,"passed_time":11.30147229,"remaining_time":51.48448487},
{"learn":[0.02771992807],"iteration":180,"passed_time":11.35706818,"remaining_time":51.38916487},
{"learn":[0.02757074202],"iteration":181,"passed_time":11.41723838,"remaining_time":51.31484063},
{"learn":[0.02738063438],"iteration":182,"passed_time":11.4757809,"remaining_time":51.23340435},
{"learn":[0.02716282625],"iteration":183,"passed_time":11.53147994,"remaining_time":51.13960671},
{"learn":[0.02699950227],"iteration":184,"passed_time":11.58709199,"remaining_time":51.0458377},
{"learn":[0.02677208272],"iteration":185,"passed_time":11.6447415,"remaining_time":50.9613956},
{"learn":[0.02658539071],"iteration":186,"passed_time":11.69999781,"remaining_time":50.86683538},
{"learn":[0.02637915438],"iteration":187,"passed_time":11.75678935,"remaining_time":50.7793242},
{"learn":[0.02625224339],"iteration":188,"passed_time":11.81405364,"remaining_time":50.69416666},
{"learn":[0.02606274985],"iteration":189,"passed_time":11.8712723,"remaining_time":50.60910822},
{"learn":[0.02580297472],"iteration":190,"passed_time":11.92659883,"remaining_time":50.51632697},
{"learn":[0.02563872314],"iteration":191,"passed_time":11.98234659,"remaining_time":50.42570858},
{"learn":[0.02543732539],"iteration":192,"passed_time":12.03735825,"remaining_time":50.3323736},
{"learn":[0.02532825354],"iteration":193,"passed_time":12.09272691,"remaining_time":50.24091695},
{"learn":[0.02507898624],"iteration":194,"passed_time":12.14992697,"remaining_time":50.15739084},
{"learn":[0.02491688883],"iteration":195,"passed_time":12.20629176,"remaining_time":50.07070701},
{"learn":[0.0248025182],"iteration":196,"passed_time":12.26162811,"remaining_time":49.98013895},
{"learn":[0.02463690003],"iteration":197,"passed_time":12.31997154,"remaining_time":49.90210695},
{"learn":[0.02444130174],"iteration":198,"passed_time":12.37795218,"remaining_time":49.82281254},
{"learn":[0.02428886731],"iteration":199,"passed_time":12.43560443,"remaining_time":49.74241771},
{"learn":[0.0240984772],"iteration":200,"passed_time":12.49390136,"remaining_time":49.66481188},
{"learn":[0.02397530462],"iteration":201,"passed_time":12.55279182,"remaining_time":49.58974192},
{"learn":[0.02383695835],"iteration":202,"passed_time":12.60810004,"remaining_time":49.50076715},
{"learn":[0.02367665852],"iteration":203,"passed_time":12.66622814,"remaining_time":49.4231255},
{"learn":[0.0235874281],"iteration":204,"passed_time":12.72262514,"remaining_time":49.3389609},
{"learn":[0.02345067027],"iteration":205,"passed_time":12.77955368,"remaining_time":49.25711468},
{"learn":[0.02332727476],"iteration":206,"passed_time":12.83441666,"remaining_time":49.16759618},
{"learn":[0.02310058432],"iteration":207,"passed_time":12.88904246,"remaining_time":49.07750781},
{"learn":[0.02296132448],"iteration":208,"passed_time":12.94810346,"remaining_time":49.00454467},
{"learn":[0.0228390247],"iteration":209,"passed_time":13.00410419,"remaining_time":48.92020146},
{"learn":[0.02267310782],"iteration":210,"passed_time":13.05788352,"remaining_time":48.82782038},
{"learn":[0.02256618968],"iteration":211,"passed_time":13.11382784,"remaining_time":48.74385064},
{"learn":[0.0224495683],"iteration":212,"passed_time":13.16966275,"remaining_time":48.65973983},
{"learn":[0.02229677872],"iteration":213,"passed_time":13.22980764,"remaining_time":48.5917234},
{"learn":[0.02219022939],"iteration":214,"passed_time":13.2876625,"remaining_time":48.51541888},
{"learn":[0.022094078],"iteration":215,"passed_time":13.34778,"remaining_time":48.44749776},
{"learn":[0.02199120801],"iteration":216,"passed_time":13.40583823,"remaining_time":48.37221812},
{"learn":[0.02187249006],"iteration":217,"passed_time":13.46007601,"remaining_time":48.28339194},
{"learn":[0.02177258649],"iteration":218,"passed_time":13.51682053,"remaining_time":48.20382115},
{"learn":[0.02167349734],"iteration":219,"passed_time":13.57255575,"remaining_time":48.12087947},
{"learn":[0.02158764306],"iteration":220,"passed_time":13.62857093,"remaining_time":48.03917084},
{"learn":[0.02148336885],"iteration":221,"passed_time":13.68388751,"remaining_time":47.9552454},
{"learn":[0.0214028418],"iteration":222,"passed_time":13.74333599,"remaining_time":47.88597338},
{"learn":[0.02128517396],"iteration":223,"passed_time":13.79868968,"remaining_time":47.80260355},
{"learn":[0.02119239286],"iteration":224,"passed_time":13.85370026,"remaining_time":47.71830091},
{"learn":[0.0211172294],"iteration":225,"passed_time":13.90804974,"remaining_time":47.63199334},
{"learn":[0.02101664873],"iteration":226,"passed_time":13.96680699,"remaining_time":47.56097712},
{"learn":[0.02086072794],"iteration":227,"passed_time":14.02424073,"remaining_time":47.48558705},
{"learn":[0.02079622415],"iteration":228,"passed_time":14.0824909,"remaining_time":47.41310256},
{"learn":[0.02072051654],"iteration":229,"passed_time":14.13733196,"remaining_time":47.32932873},
{"learn":[0.02058314668],"iteration":230,"passed_time":14.19316589,"remaining_time":47.24911068},
{"learn":[0.02049646673],"iteration":231,"passed_time":14.24979292,"remaining_time":47.17172828},
{"learn":[0.02040073025],"iteration":232,"passed_time":14.30510766,"remaining_time":47.09020418},
{"learn":[0.02032099808],"iteration":233,"passed_time":14.36075166,"remaining_time":47.00998194},
{"learn":[0.02027203391],"iteration":234,"passed_time":14.41925309,"remaining_time":46.9392707},
{"learn":[0.02017232194],"iteration":235,"passed_time":14.47854718,"remaining_time":46.87122899},
{"learn":[0.0201107303],"iteration":236,"passed_time":14.53443459,"remaining_time":46.79229364},
{"learn":[0.02000253294],"iteration":237,"passed_time":14.59253759,"remaining_time":46.72064555},
{"learn":[0.01994862926],"iteration":238,"passed_time":14.64795105,"remaining_time":46.64054708},
{"learn":[0.01986622868],"iteration":239,"passed_time":14.7038993,"remaining_time":46.56234777},
{"learn":[0.01973455991],"iteration":240,"passed_time":14.76068338,"remaining_time":46.4869655},
{"learn":[0.01960655572],"iteration":241,"passed_time":14.81622399,"remaining_time":46.40784207},
{"learn":[0.01951876546],"iteration":242,"passed_time":14.87265355,"remaining_time":46.33168204},
{"learn":[0.01944973863],"iteration":243,"passed_time":14.9302493,"remaining_time":46.259297},
{"learn":[0.0193433879],"iteration":244,"passed_time":14.98469041,"remaining_time":46.17731125},
{"learn":[0.01925216695],"iteration":245,"passed_time":15.04195661,"remaining_time":46.10420848},
{"learn":[0.01918406385],"iteration":246,"passed_time":15.0973198,"remaining_time":46.02543241},
{"learn":[0.01911035948],"iteration":247,"passed_time":15.15333781,"remaining_time":45.94883079},
{"learn":[0.01897205436],"iteration":248,"passed_time":15.20988311,"remaining_time":45.87398479},
{"learn":[0.01888862326],"iteration":249,"passed_time":15.26536758,"remaining_time":45.79610274},
{"learn":[0.01878843122],"iteration":250,"passed_time":15.32241338,"remaining_time":45.72305825},
{"learn":[0.01870092603],"iteration":251,"passed_time":15.37799497,"remaining_time":45.64579458},
{"learn":[0.01861499652],"iteration":252,"passed_time":15.43328191,"remaining_time":45.56783235},
{"learn":[0.01847635273],"iteration":253,"passed_time":15.48825234,"remaining_time":45.48911909},
{"learn":[0.01841612792],"iteration":254,"passed_time":15.54511196,"remaining_time":45.4161114},
{"learn":[0.01836557732],"iteration":255,"passed_time":15.60011769,"remaining_time":45.33784205},
{"learn":[0.01830219484],"iteration":256,"passed_time":15.65564459,"remaining_time":45.26126044},
{"learn":[0.01819641931],"iteration":257,"passed_time":15.70873558,"remaining_time":45.17783644},
{"learn":[0.01807110263],"iteration":258,"passed_time":15.76192446,"remaining_time":45.09492673},
{"learn":[0.01800739006],"iteration":259,"passed_time":15.81595493,"remaining_time":45.01464096},
{"learn":[0.01791894264],"iteration":260,"passed_time":15.87089464,"remaining_time":44.9371308},
{"learn":[0.01782529376],"iteration":261,"passed_time":15.92486897,"remaining_time":44.85707367},
{"learn":[0.01773265201],"iteration":262,"passed_time":15.97911828,"remaining_time":44.77798545},
{"learn":[0.01765422403],"iteration":263,"passed_time":16.03296614,"remaining_time":44.6979662},
{"learn":[0.01752510093],"iteration":264,"passed_time":16.08677075,"remaining_time":44.61802454},
{"learn":[0.01747099858],"iteration":265,"passed_time":16.14184921,"remaining_time":44.54179443},
{"learn":[0.01738548814],"iteration":266,"passed_time":16.19776862,"remaining_time":44.46803145},
{"learn":[0.01726938942],"iteration":267,"passed_time":16.25163548,"remaining_time":44.38879542},
{"learn":[0.01718915869],"iteration":268,"passed_time":16.30530954,"remaining_time":44.30922405},
{"learn":[0.01711587268],"iteration":269,"passed_time":16.36062858,"remaining_time":44.23429209},
{"learn":[0.0170157208],"iteration":270,"passed_time":16.41488373,"remaining_time":44.15664294},
{"learn":[0.01696533366],"iteration":271,"passed_time":16.46848993,"remaining_time":44.07742894},
{"learn":[0.01685242822],"iteration":272,"passed_time":16.52297694,"remaining_time":44.00074811},
{"learn":[0.0167790544],"iteration":273,"passed_time":16.57879874,"remaining_time":43.92776601},
{"learn":[0.01670963509],"iteration":274,"passed_time":16.63770134,"remaining_time":43.86303081},
{"learn":[0.01664458068],"iteration":275,"passed_time":16.69449724,"remaining_time":43.79281161},
{"learn":[0.01651012294],"iteration":276,"passed_time":16.75203816,"remaining_time":43.7246339},
{"learn":[0.01646963353],"iteration":277,"passed_time":16.80959127,"remaining_time":43.65656438},
{"learn":[0.01641301817],"iteration":278,"passed_time":16.86464697,"remaining_time":43.58211637},
{"learn":[0.01633991555],"iteration":279,"passed_time":16.919923,"remaining_time":43.50837343},
{"learn":[0.01626327596],"iteration":280,"passed_time":16.97466762,"remaining_time":43.4334022},
{"learn":[0.01620241867],"iteration":281,"passed_time":17.03052083,"remaining_time":43.361397},
{"learn":[0.01615749175],"iteration":282,"passed_time":17.08747863,"remaining_time":43.29230452},
{"learn":[0.01609737528],"iteration":283,"passed_time":17.14547169,"remaining_time":43.22590749},
{"learn":[0.01605318426],"iteration":284,"passed_time":17.20061059,"remaining_time":43.15240902},
{"learn":[0.01595166218],"iteration":285,"passed_time":17.25678654,"remaining_time":43.08162793},
{"learn":[0.01590522809],"iteration":286,"passed_time":17.31312153,"remaining_time":43.01134372},
{"learn":[0.01585655133],"iteration":287,"passed_time":17.36993234,"remaining_time":42.94233272},
{"learn":[0.01581173835],"iteration":288,"passed_time":17.42878125,"remaining_time":42.8784203},
{"learn":[0.0157619608],"iteration":289,"passed_time":17.48414616,"remaining_time":42.806013},
{"learn":[0.0157007591],"iteration":290,"passed_time":17.53780323,"remaining_time":42.72956183},
{"learn":[0.01566027114],"iteration":291,"passed_time":17.59145832,"remaining_time":42.65326195},
{"learn":[0.01561531977],"iteration":292,"passed_time":17.65017366,"remaining_time":42.58932689},
{"learn":[0.01556840292],"iteration":293,"passed_time":17.70357282,"remaining_time":42.51266126},
{"learn":[0.01550285786],"iteration":294,"passed_time":17.75734715,"remaining_time":42.43704996},
{"learn":[0.01545912046],"iteration":295,"passed_time":17.8104261,"remaining_time":42.35993234},
{"learn":[0.01539047176],"iteration":296,"passed_time":17.86470768,"remaining_time":42.28582324},
{"learn":[0.01529762106],"iteration":297,"passed_time":17.91878575,"remaining_time":42.21136778},
{"learn":[0.01522919041],"iteration":298,"passed_time":17.97215555,"remaining_time":42.13538808},
{"learn":[0.01517144642],"iteration":299,"passed_time":18.02564293,"remaining_time":42.05983351},
{"learn":[0.01509542883],"iteration":300,"passed_time":18.08088229,"remaining_time":41.98849409},
{"learn":[0.01502206877],"iteration":301,"passed_time":18.13433025,"remaining_time":41.9131209},
{"learn":[0.0149541416],"iteration":302,"passed_time":18.18751922,"remaining_time":41.83729668},
{"learn":[0.01491294728],"iteration":303,"passed_time":18.24089996,"remaining_time":41.76206043},
{"learn":[0.01485800396],"iteration":304,"passed_time":18.2960733,"remaining_time":41.69105227},
{"learn":[0.01477239115],"iteration":305,"passed_time":18.34860891,"remaining_time":41.61416531},
{"learn":[0.01473183606],"iteration":306,"passed_time":18.40316516,"remaining_time":41.54199822},
{"learn":[0.01468783892],"iteration":307,"passed_time":18.45656008,"remaining_time":41.46733629},
{"learn":[0.01463663712],"iteration":308,"passed_time":18.50969472,"remaining_time":41.39222994},
{"learn":[0.01459792015],"iteration":309,"passed_time":18.56240736,"remaining_time":41.31632607},
{"learn":[0.01453905498],"iteration":310,"passed_time":18.61587082,"remaining_time":41.2422347},
{"learn":[0.01450005292],"iteration":311,"passed_time":18.66948155,"remaining_time":41.16860034},
{"learn":[0.01444037943],"iteration":312,"passed_time":18.72283013,"remaining_time":41.09451853},
{"learn":[0.01435728758],"iteration":313,"passed_time":18.77916643,"remaining_time":41.02709609},
{"learn":[0.01431032382],"iteration":314,"passed_time":18.83530095,"remaining_time":40.95930524},
{"learn":[0.01426929761],"iteration":315,"passed_time":18.88947524,"remaining_time":40.88734513},
{"learn":[0.01421239341],"iteration":316,"passed_time":18.94275371,"remaining_time":40.81356714},
{"learn":[0.01417085524],"iteration":317,"passed_time":18.99600595,"remaining_time":40.73986182},
{"learn":[0.01412864284],"iteration":318,"passed_time":19.05110749,"remaining_time":40.67023261},
{"learn":[0.01406244325],"iteration":319,"passed_time":19.10485012,"remaining_time":40.5978065},
{"learn":[0.01403380823],"iteration":320,"passed_time":19.15915027,"remaining_time":40.52667611},
{"learn":[0.01397397099],"iteration":321,"passed_time":19.21160319,"remaining_time":40.45176076},
{"learn":[0.01392163452],"iteration":322,"passed_time":19.2639455,"remaining_time":40.37675264},
{"learn":[0.01385264284],"iteration":323,"passed_time":19.31484395,"remaining_time":40.29887195},
{"learn":[0.01377730233],"iteration":324,"passed_time":19.36477581,"remaining_time":40.21914975},
{"learn":[0.01374537554],"iteration":325,"passed_time":19.41413307,"remaining_time":40.13842235},
{"learn":[0.01366864163],"iteration":326,"passed_time":19.4634703,"remaining_time":40.0578456},
{"learn":[0.01362787083],"iteration":327,"passed_time":19.51621399,"remaining_time":39.98443841},
{"learn":[0.01358498248],"iteration":328,"passed_time":19.56955721,"remaining_time":39.91237959},
{"learn":[0.01356046542],"iteration":329,"passed_time":19.62242774,"remaining_time":39.8394745},
{"learn":[0.01350820109],"iteration":330,"passed_time":19.67595977,"remaining_time":39.76802745},
{"learn":[0.01342873429],"iteration":331,"passed_time":19.72926206,"remaining_time":39.69622607},
{"learn":[0.01338355421],"iteration":332,"passed_time":19.78689589,"remaining_time":39.63321188},
{"learn":[0.01333541579],"iteration":333,"passed_time":19.84044984,"remaining_time":39.56209459},
{"learn":[0.01327235396],"iteration":334,"passed_time":19.89570076,"remaining_time":39.49445076},
{"learn":[0.01323732476],"iteration":335,"passed_time":19.94978238,"remaining_time":39.42456995},
{"learn":[0.01318051595],"iteration":336,"passed_time":20.00351218,"remaining_time":39.35409072},
{"learn":[0.01311391554],"iteration":337,"passed_time":20.06323044,"remaining_time":39.29543951},
{"learn":[0.01307180824],"iteration":338,"passed_time":20.12049645,"remaining_time":39.23200045},
{"learn":[0.01302159005],"iteration":339,"passed_time":20.18131029,"remaining_time":39.17548467},
{"learn":[0.01297350787],"iteration":340,"passed_time":20.23854187,"remaining_time":39.1120208},
{"learn":[0.01293610077],"iteration":341,"passed_time":20.29520838,"remaining_time":39.04750617},
{"learn":[0.01289080064],"iteration":342,"passed_time":20.35307583,"remaining_time":38.98533767},
{"learn":[0.01286710717],"iteration":343,"passed_time":20.41316924,"remaining_time":38.92743901},
{"learn":[0.01284227702],"iteration":344,"passed_time":20.4717948,"remaining_time":38.86674084},
{"learn":[0.01279675305],"iteration":345,"passed_time":20.52994925,"remaining_time":38.80516419},
{"learn":[0.01277199591],"iteration":346,"passed_time":20.58638355,"remaining_time":38.74037019},
{"learn":[0.01273178047],"iteration":347,"passed_time":20.64327499,"remaining_time":38.67648073},
{"learn":[0.01269006082],"iteration":348,"passed_time":20.69893142,"remaining_time":38.61032766},
{"learn":[0.01266657854],"iteration":349,"passed_time":20.75481494,"remaining_time":38.54465631},
{"learn":[0.01262094953],"iteration":350,"passed_time":20.81449756,"remaining_time":38.48606529},
{"learn":[0.0125447593],"iteration":351,"passed_time":20.87262389,"remaining_time":38.42460308},
{"learn":[0.01251336995],"iteration":352,"passed_time":20.92903598,"remaining_time":38.36001779},
{"learn":[0.01246571043],"iteration":353,"passed_time":20.98487083,"remaining_time":38.29442531},
{"learn":[0.01243707924],"iteration":354,"passed_time":21.04179941,"remaining_time":38.23087499},
{"learn":[0.01239155114],"iteration":355,"passed_time":21.09996262,"remaining_time":38.1695953},
{"learn":[0.01236359855],"iteration":356,"passed_time":21.15677612,"remaining_time":38.10590209},
{"learn":[0.01232269283],"iteration":357,"passed_time":21.21306408,"remaining_time":38.04130486},
{"learn":[0.01225131503],"iteration":358,"passed_time":21.26653397,"remaining_time":37.97172222},
{"learn":[0.0122025955],"iteration":359,"passed_time":21.31834576,"remaining_time":37.89928135},
{"learn":[0.01217343736],"iteration":360,"passed_time":21.37376195,"remaining_time":37.83333486},
{"learn":[0.0121373466],"iteration":361,"passed_time":21.42626368,"remaining_time":37.76231001},
{"learn":[0.01209703864],"iteration":362,"passed_time":21.47726621,"remaining_time":37.6887564},
{"learn":[0.01205670289],"iteration":363,"passed_time":21.52783944,"remaining_time":37.6145766},
{"learn":[0.01202020432],"iteration":364,"passed_time":21.57824208,"remaining_time":37.54022937},
{"learn":[0.01199393604],"iteration":365,"passed_time":21.62877732,"remaining_time":37.46624269},
{"learn":[0.01196764641],"iteration":366,"passed_time":21.67861015,"remaining_time":37.39117228},
{"learn":[0.01192992914],"iteration":367,"passed_time":21.73289039,"remaining_time":37.32387697},
{"learn":[0.01190135636],"iteration":368,"passed_time":21.7862557,"remaining_time":37.25508766},
{"learn":[0.01187606282],"iteration":369,"passed_time":21.84194261,"remaining_time":37.19033471},
{"learn":[0.01185377555],"iteration":370,"passed_time":21.8948316,"remaining_time":37.120887},
{"learn":[0.01182583381],"iteration":371,"passed_time":21.94797294,"remaining_time":37.05195432},
{"learn":[0.01178866208],"iteration":372,"passed_time":22.00248634,"remaining_time":36.9854127},
{"learn":[0.01176126647],"iteration":373,"passed_time":22.05762822,"remaining_time":36.91998734},
{"learn":[0.01173264943],"iteration":374,"passed_time":22.11142085,"remaining_time":36.85236808},
{"learn":[0.01170848201],"iteration":375,"passed_time":22.16864788,"remaining_time":36.79052202},
{"learn":[0.01167721689],"iteration":376,"passed_time":22.22322036,"remaining_time":36.72431375},
{"learn":[0.01165535766],"iteration":377,"passed_time":22.27850343,"remaining_time":36.65933633},
{"learn":[0.01162582851],"iteration":378,"passed_time":22.3359926,"remaining_time":36.59802481},
{"learn":[0.01157001363],"iteration":379,"passed_time":22.39304707,"remaining_time":36.53602416},
{"learn":[0.01154649339],"iteration":380,"passed_time":22.44887492,"remaining_time":36.47205663},
{"learn":[0.01151564965],"iteration":381,"passed_time":22.50453799,"remaining_time":36.40786513},
{"learn":[0.01146829845],"iteration":382,"passed_time":22.55973978,"remaining_time":36.34297504},
{"learn":[0.01143976469],"iteration":383,"passed_time":22.61720341,"remaining_time":36.2817638},
{"learn":[0.01140169426],"iteration":384,"passed_time":22.67624277,"remaining_time":36.2230891},
{"learn":[0.01136630566],"iteration":385,"passed_time":22.73494804,"remaining_time":36.16388108},
{"learn":[0.01132660643],"iteration":386,"passed_time":22.79423138,"remaining_time":36.10559131},
{"learn":[0.01130726913],"iteration":387,"passed_time":22.85238255,"remaining_time":36.04551061},
{"learn":[0.01128122017],"iteration":388,"passed_time":22.90998997,"remaining_time":35.98458579},
{"learn":[0.0112453014],"iteration":389,"passed_time":22.96501025,"remaining_time":35.91963141},
{"learn":[0.01121023277],"iteration":390,"passed_time":23.02141165,"remaining_time":35.85687901},
{"learn":[0.01117495509],"iteration":391,"passed_time":23.07650415,"remaining_time":35.79212889},
{"learn":[0.01114215577],"iteration":392,"passed_time":23.13145727,"remaining_time":35.72721262},
{"learn":[0.01111304034],"iteration":393,"passed_time":23.1869666,"remaining_time":35.66320243},
{"learn":[0.01108914621],"iteration":394,"passed_time":23.2428728,"remaining_time":35.59984315},
{"learn":[0.01105630726],"iteration":395,"passed_time":23.29741447,"remaining_time":35.53444026},
{"learn":[0.01103145083],"iteration":396,"passed_time":23.34838773,"remaining_time":35.46367205},
{"learn":[0.01101296383],"iteration":397,"passed_time":23.40316464,"remaining_time":35.39875657},
{"learn":[0.01098938171],"iteration":398,"passed_time":23.45604938,"remaining_time":35.3310418},
{"learn":[0.01096924772],"iteration":399,"passed_time":23.51219495,"remaining_time":35.26829242},
{"learn":[0.01093684905],"iteration":400,"passed_time":23.56490872,"remaining_time":35.20044968},
{"learn":[0.0109110116],"iteration":401,"passed_time":23.61852597,"remaining_time":35.1340262},
{"learn":[0.01087627722],"iteration":402,"passed_time":23.67523728,"remaining_time":35.07224977},
{"learn":[0.010853673],"iteration":403,"passed_time":23.73109458,"remaining_time":35.00923853},
{"learn":[0.01082598138],"iteration":404,"passed_time":23.78495368,"remaining_time":34.94332701},
{"learn":[0.01077471436],"iteration":405,"passed_time":23.84248265,"remaining_time":34.88284407},
{"learn":[0.01073994804],"iteration":406,"passed_time":23.89830574,"remaining_time":34.81989018},
{"learn":[0.01069844126],"iteration":407,"passed_time":23.95517768,"remaining_time":34.75849311},
{"learn":[0.01067446365],"iteration":408,"passed_time":24.0146415,"remaining_time":34.70086339},
{"learn":[0.01064558172],"iteration":409,"passed_time":24.07357522,"remaining_time":34.6424619},
{"learn":[0.01061976408],"iteration":410,"passed_time":24.13378559,"remaining_time":34.58588738},
{"learn":[0.01059623704],"iteration":411,"passed_time":24.18620139,"remaining_time":34.51817092},
{"learn":[0.01057351249],"iteration":412,"passed_time":24.24533533,"remaining_time":34.46007709},
{"learn":[0.01054320084],"iteration":413,"passed_time":24.29926272,"remaining_time":34.39460858},
{"learn":[0.01051783076],"iteration":414,"passed_time":24.35161473,"remaining_time":34.32697498},
{"learn":[0.01047993554],"iteration":415,"passed_time":24.40424493,"remaining_time":34.25980538},
{"learn":[0.01044312021],"iteration":416,"passed_time":24.46258432,"remaining_time":34.20068743},
{"learn":[0.01041958312],"iteration":417,"passed_time":24.51491856,"remaining_time":34.13321196},
{"learn":[0.01038560773],"iteration":418,"passed_time":24.57312982,"remaining_time":34.07395806},
{"learn":[0.01036617335],"iteration":419,"passed_time":24.63251166,"remaining_time":34.01632563},
{"learn":[0.01033954512],"iteration":420,"passed_time":24.68831661,"remaining_time":33.9537656},
{"learn":[0.01029880903],"iteration":421,"passed_time":24.74742665,"remaining_time":33.89576446},
{"learn":[0.0102651459],"iteration":422,"passed_time":24.80602784,"remaining_time":33.83706397},
{"learn":[0.01024675392],"iteration":423,"passed_time":24.86406366,"remaining_time":33.77759592},
{"learn":[0.01022103239],"iteration":424,"passed_time":24.92153338,"remaining_time":33.71736869},
{"learn":[0.01018772974],"iteration":425,"passed_time":24.97915211,"remaining_time":33.65735519},
{"learn":[0.01016642548],"iteration":426,"passed_time":25.03760228,"remaining_time":33.59846863},
{"learn":[0.0101481657],"iteration":427,"passed_time":25.09558404,"remaining_time":33.53895811},
{"learn":[0.01012443713],"iteration":428,"passed_time":25.15598936,"remaining_time":33.48268048},
{"learn":[0.01009623736],"iteration":429,"passed_time":25.2131628,"remaining_time":33.42209952},
{"learn":[0.01004101026],"iteration":430,"passed_time":25.27113218,"remaining_time":33.36258517},
{"learn":[0.0100172538],"iteration":431,"passed_time":25.32625826,"remaining_time":33.29933956},
{"learn":[0.01000351335],"iteration":432,"passed_time":25.3857628,"remaining_time":33.24186492},
{"learn":[0.009963978996],"iteration":433,"passed_time":25.44194824,"remaining_time":33.18005231},
{"learn":[0.009931576636],"iteration":434,"passed_time":25.49697131,"remaining_time":33.11675584},
{"learn":[0.009906680636],"iteration":435,"passed_time":25.55577347,"remaining_time":33.05838587},
{"learn":[0.009879990633],"iteration":436,"passed_time":25.61242444,"remaining_time":32.99724247},
{"learn":[0.009860375456],"iteration":437,"passed_time":25.67075807,"remaining_time":32.93827862},
{"learn":[0.009836541058],"iteration":438,"passed_time":25.72970156,"remaining_time":32.88009698},
{"learn":[0.009825002989],"iteration":439,"passed_time":25.78680664,"remaining_time":32.81957209},
{"learn":[0.00980112595],"iteration":440,"passed_time":25.84553136,"remaining_time":32.76111572},
{"learn":[0.009777042823],"iteration":441,"passed_time":25.90493016,"remaining_time":32.70350912},
{"learn":[0.009748000708],"iteration":442,"passed_time":25.96216389,"remaining_time":32.64317221},
{"learn":[0.009738656193],"iteration":443,"passed_time":26.01915582,"remaining_time":32.58254648},
{"learn":[0.009708024285],"iteration":444,"passed_time":26.08124418,"remaining_time":32.5282933},
{"learn":[0.00968268568],"iteration":445,"passed_time":26.14152198,"remaining_time":32.471756},
{"learn":[0.009653085474],"iteration":446,"passed_time":26.20005418,"remaining_time":32.41304242},
{"learn":[0.009624458801],"iteration":447,"passed_time":26.25588179,"remaining_time":32.3509972},
{"learn":[0.009594365056],"iteration":448,"passed_time":26.31181894,"remaining_time":32.28911412},
{"learn":[0.009579465867],"iteration":449,"passed_time":26.36646434,"remaining_time":32.22567864},
{"learn":[0.009565736562],"iteration":450,"passed_time":26.42299464,"remaining_time":32.16457663},
{"learn":[0.009539549183],"iteration":451,"passed_time":26.48179188,"remaining_time":32.10624325},
{"learn":[0.009523416856],"iteration":452,"passed_time":26.53832996,"remaining_time":32.04517989},
{"learn":[0.009499421706],"iteration":453,"passed_time":26.59562608,"remaining_time":31.98504811},
{"learn":[0.009477721669],"iteration":454,"passed_time":26.65440347,"remaining_time":31.92670306},
{"learn":[0.009455835403],"iteration":455,"passed_time":26.71035096,"remaining_time":31.86498009},
{"learn":[0.009436083154],"iteration":456,"passed_time":26.76476153,"remaining_time":31.80145626},
{"learn":[0.009415329104],"iteration":457,"passed_time":26.81939999,"remaining_time":31.73824192},
{"learn":[0.009385899497],"iteration":458,"passed_time":26.8744672,"remaining_time":31.67557028},
{"learn":[0.009370919379],"iteration":459,"passed_time":26.93046083,"remaining_time":31.61401923},
{"learn":[0.009351502132],"iteration":460,"passed_time":26.98586322,"remaining_time":31.55180103},
{"learn":[0.009328929635],"iteration":461,"passed_time":27.04088303,"remaining_time":31.48916682},
{"learn":[0.009314738825],"iteration":462,"passed_time":27.09878139,"remaining_time":31.42990412},
{"learn":[0.009292604923],"iteration":463,"passed_time":27.155766,"remaining_time":31.36959176},
{"learn":[0.009278840333],"iteration":464,"passed_time":27.20972435,"remaining_time":31.30581188},
{"learn":[0.009250092091],"iteration":465,"passed_time":27.26508006,"remaining_time":31.24367544},
{"learn":[0.009226274714],"iteration":466,"passed_time":27.32051869,"remaining_time":31.18166266},
{"learn":[0.009211710563],"iteration":467,"passed_time":27.37718401,"remaining_time":31.12107243},
{"learn":[0.009194413596],"iteration":468,"passed_time":27.43503672,"remaining_time":31.06184328},
{"learn":[0.009178988265],"iteration":469,"passed_time":27.4923746,"remaining_time":31.00203945},
{"learn":[0.009151710665],"iteration":470,"passed_time":27.55018673,"remaining_time":30.94277873},
{"learn":[0.009125562338],"iteration":471,"passed_time":27.60578648,"remaining_time":30.88104928},
{"learn":[0.009107076891],"iteration":472,"passed_time":27.6603681,"remaining_time":30.81821139},
{"learn":[0.009084437804],"iteration":473,"passed_time":27.71915886,"remaining_time":30.76007924},
{"learn":[0.009069334139],"iteration":474,"passed_time":27.7764005,"remaining_time":30.70023213},
{"learn":[0.009061506832],"iteration":475,"passed_time":27.83089628,"remaining_time":30.63737321},
{"learn":[0.00904721031],"iteration":476,"passed_time":27.88555522,"remaining_time":30.57472826},
{"learn":[0.009035038129],"iteration":477,"passed_time":27.93992477,"remaining_time":30.51180069},
{"learn":[0.009000521732],"iteration":478,"passed_time":27.99449785,"remaining_time":30.44913023},
{"learn":[0.008983748802],"iteration":479,"passed_time":28.04880522,"remaining_time":30.38620565},
{"learn":[0.008955418454],"iteration":480,"passed_time":28.10551793,"remaining_time":30.32591228},
{"learn":[0.008938624771],"iteration":481,"passed_time":28.16181388,"remaining_time":30.26518587},
{"learn":[0.008920803051],"iteration":482,"passed_time":28.21491044,"remaining_time":30.20105321},
{"learn":[0.00890263002],"iteration":483,"passed_time":28.26863753,"remaining_time":30.13763836},
{"learn":[0.008885474979],"iteration":484,"passed_time":28.32137052,"remaining_time":30.07320787},
{"learn":[0.008860595],"iteration":485,"passed_time":28.37480511,"remaining_time":30.00956755},
{"learn":[0.008840805235],"iteration":486,"passed_time":28.42809755,"remaining_time":29.94581939},
{"learn":[0.00881551738],"iteration":487,"passed_time":28.48315166,"remaining_time":29.8839624},
{"learn":[0.008798206336],"iteration":488,"passed_time":28.53589497,"remaining_time":29.81971846},
{"learn":[0.008774836113],"iteration":489,"passed_time":28.5905348,"remaining_time":29.7574954},
{"learn":[0.008760361733],"iteration":490,"passed_time":28.64688484,"remaining_time":29.69707614},
{"learn":[0.008753925079],"iteration":491,"passed_time":28.70286407,"remaining_time":29.63629054},
{"learn":[0.008733238011],"iteration":492,"passed_time":28.75691274,"remaining_time":29.57353906},
{"learn":[0.008713099541],"iteration":493,"passed_time":28.81240205,"remaining_time":29.51229845},
{"learn":[0.008691766214],"iteration":494,"passed_time":28.86953851,"remaining_time":29.45276151},
{"learn":[0.008660840114],"iteration":495,"passed_time":28.92342307,"remaining_time":29.38992989},
{"learn":[0.00864459904],"iteration":496,"passed_time":28.97750333,"remaining_time":29.32733234},
{"learn":[0.00863410351],"iteration":497,"passed_time":29.03155891,"remaining_time":29.26474412},
{"learn":[0.008614076839],"iteration":498,"passed_time":29.08867774,"remaining_time":29.20526563},
{"learn":[0.008590839662],"iteration":499,"passed_time":29.14220883,"remaining_time":29.14220883},
{"learn":[0.008570298824],"iteration":500,"passed_time":29.20103486,"remaining_time":29.08446386},
{"learn":[0.008552777443],"iteration":501,"passed_time":29.25808449,"remaining_time":29.02495235},
{"learn":[0.008536523973],"iteration":502,"passed_time":29.31082837,"remaining_time":28.96119622},
{"learn":[0.008524588952],"iteration":503,"passed_time":29.36777363,"remaining_time":28.90161849},
{"learn":[0.008511667748],"iteration":504,"passed_time":29.42224501,"remaining_time":28.8396263},
{"learn":[0.008487387391],"iteration":505,"passed_time":29.47805126,"remaining_time":28.77896704},
{"learn":[0.008472086919],"iteration":506,"passed_time":29.53504428,"remaining_time":28.71948092},
{"learn":[0.008456871226],"iteration":507,"passed_time":29.59024549,"remaining_time":28.65826926},
{"learn":[0.008441465748],"iteration":508,"passed_time":29.65073752,"remaining_time":28.60218491},
{"learn":[0.008425060268],"iteration":509,"passed_time":29.70653885,"remaining_time":28.54157654},
{"learn":[0.008407453435],"iteration":510,"passed_time":29.76705579,"remaining_time":28.48549957},
{"learn":[0.008385536173],"iteration":511,"passed_time":29.82866041,"remaining_time":28.43044195},
{"learn":[0.008370203021],"iteration":512,"passed_time":29.88515355,"remaining_time":28.37050639},
{"learn":[0.008351869145],"iteration":513,"passed_time":29.9363718,"remaining_time":28.30559668},
{"learn":[0.008341418509],"iteration":514,"passed_time":29.98981786,"remaining_time":28.24283817},
{"learn":[0.008333496757],"iteration":515,"passed_time":30.04325585,"remaining_time":28.1801082},
{"learn":[0.008318748152],"iteration":516,"passed_time":30.10245522,"remaining_time":28.12279666},
{"learn":[0.008300966928],"iteration":517,"passed_time":30.15621858,"remaining_time":28.0604196},
{"learn":[0.008287542302],"iteration":518,"passed_time":30.21070371,"remaining_time":27.99874467},
{"learn":[0.008273315251],"iteration":519,"passed_time":30.27157017,"remaining_time":27.94298785},
{"learn":[0.008249676377],"iteration":520,"passed_time":30.32453793,"remaining_time":27.87994946},
{"learn":[0.0082286294],"iteration":521,"passed_time":30.38200232,"remaining_time":27.82106726},
{"learn":[0.008209341216],"iteration":522,"passed_time":30.44092038,"remaining_time":27.7635163},
{"learn":[0.008196438464],"iteration":523,"passed_time":30.49853257,"remaining_time":27.70477386},
{"learn":[0.008177799177],"iteration":524,"passed_time":30.5581051,"remaining_time":27.64780938},
{"learn":[0.00815823572],"iteration":525,"passed_time":30.61770668,"remaining_time":27.59086116},
{"learn":[0.008135745825],"iteration":526,"passed_time":30.67575621,"remaining_time":27.53250984},
{"learn":[0.008125755052],"iteration":527,"passed_time":30.73220135,"remaining_time":27.47272545},
{"learn":[0.008107908783],"iteration":528,"passed_time":30.78797797,"remaining_time":27.41235846},
{"learn":[0.008095152862],"iteration":529,"passed_time":30.84426716,"remaining_time":27.35246333},
{"learn":[0.008079150681],"iteration":530,"passed_time":30.90318447,"remaining_time":27.29490304},
{"learn":[0.008052241651],"iteration":531,"passed_time":30.95871119,"remaining_time":27.23435495},
{"learn":[0.008036325247],"iteration":532,"passed_time":31.01571362,"remaining_time":27.17511869},
{"learn":[0.00801325133],"iteration":533,"passed_time":31.07197522,"remaining_time":27.11524429},
{"learn":[0.007994443256],"iteration":534,"passed_time":31.12669802,"remaining_time":27.05404594},
{"learn":[0.00797609026],"iteration":535,"passed_time":31.18277126,"remaining_time":26.99404079},
{"learn":[0.007965315594],"iteration":536,"passed_time":31.24029864,"remaining_time":26.93530405},
{"learn":[0.007951881406],"iteration":537,"passed_time":31.29962399,"remaining_time":26.87811577},
{"learn":[0.007935895104],"iteration":538,"passed_time":31.35541031,"remaining_time":26.81789268},
{"learn":[0.007907624379],"iteration":539,"passed_time":31.41031826,"remaining_time":26.75693778},
{"learn":[0.007894562956],"iteration":540,"passed_time":31.46453251,"remaining_time":26.69541668},
{"learn":[0.00788082537],"iteration":541,"passed_time":31.51977489,"remaining_time":26.63479133},
{"learn":[0.007867379858],"iteration":542,"passed_time":31.57714155,"remaining_time":26.57597364},
{"learn":[0.007849982252],"iteration":543,"passed_time":31.63284437,"remaining_time":26.5157666},
{"learn":[0.007834909304],"iteration":544,"passed_time":31.68911233,"remaining_time":26.45604791},
{"learn":[0.007825905612],"iteration":545,"passed_time":31.74404991,"remaining_time":26.39523564},
{"learn":[0.007808592593],"iteration":546,"passed_time":31.79867796,"remaining_time":26.33418851},
{"learn":[0.007798812576],"iteration":547,"passed_time":31.85375286,"remaining_time":26.27353338},
{"learn":[0.007787374933],"iteration":548,"passed_time":31.90851906,"remaining_time":26.21264498},
{"learn":[0.007772341474],"iteration":549,"passed_time":31.96265727,"remaining_time":26.15126504},
{"learn":[0.007761512178],"iteration":550,"passed_time":32.01879414,"remaining_time":26.09154005},
{"learn":[0.007746128914],"iteration":551,"passed_time":32.07464967,"remaining_time":26.03159973},
{"learn":[0.00772777464],"iteration":552,"passed_time":32.13002671,"remaining_time":25.97128741},
{"learn":[0.007713510593],"iteration":553,"passed_time":32.18480491,"remaining_time":25.91051081},
{"learn":[0.007702829335],"iteration":554,"passed_time":32.24025022,"remaining_time":25.85029072},
{"learn":[0.007688224255],"iteration":555,"passed_time":32.29642918,"remaining_time":25.79067366},
{"learn":[0.007675181037],"iteration":556,"passed_time":32.35189692,"remaining_time":25.73050329},
{"learn":[0.007667409861],"iteration":557,"passed_time":32.4145718,"remaining_time":25.67605867},
{"learn":[0.007655137005],"iteration":558,"passed_time":32.47121641,"remaining_time":25.61682725},
{"learn":[0.007644266481],"iteration":559,"passed_time":32.52965344,"remaining_time":25.55901342},
{"learn":[0.007634831591],"iteration":560,"passed_time":32.58456967,"remaining_time":25.49844222},
{"learn":[0.007617687262],"iteration":561,"passed_time":32.64245587,"remaining_time":25.44020582},
{"learn":[0.007606470521],"iteration":562,"passed_time":32.69879683,"remaining_time":25.38077126},
{"learn":[0.007596943412],"iteration":563,"passed_time":32.75462623,"remaining_time":25.32095219},
{"learn":[0.007574873978],"iteration":564,"passed_time":32.8101083,"remaining_time":25.26087984},
{"learn":[0.007562902585],"iteration":565,"passed_time":32.86432216,"remaining_time":25.19985127},
{"learn":[0.007553448943],"iteration":566,"passed_time":32.91790318,"remaining_time":25.13836345},
{"learn":[0.007526787218],"iteration":567,"passed_time":32.97678249,"remaining_time":25.08093316},
{"learn":[0.007512620911],"iteration":568,"passed_time":33.03203286,"remaining_time":25.02074896},
{"learn":[0.007497618818],"iteration":569,"passed_time":33.08511681,"remaining_time":24.95894777},
{"learn":[0.007477164314],"iteration":570,"passed_time":33.13894177,"remaining_time":24.89773384},
{"learn":[0.007459698612],"iteration":571,"passed_time":33.19364886,"remaining_time":24.83720579},
{"learn":[0.007445724546],"iteration":572,"passed_time":33.25008296,"remaining_time":24.77798503},
{"learn":[0.007436815247],"iteration":573,"passed_time":33.30490598,"remaining_time":24.71757831},
{"learn":[0.007424369835],"iteration":574,"passed_time":33.37016321,"remaining_time":24.66490324},
{"learn":[0.007405542014],"iteration":575,"passed_time":33.43078118,"remaining_time":24.60876948},
{"learn":[0.007382527769],"iteration":576,"passed_time":33.49029972,"remaining_time":24.55181418},
{"learn":[0.007373085034],"iteration":577,"passed_time":33.54704376,"remaining_time":24.49282433},
{"learn":[0.007359836769],"iteration":578,"passed_time":33.61067805,"remaining_time":24.43885226},
{"learn":[0.007349156136],"iteration":579,"passed_time":33.67206033,"remaining_time":24.3832161},
{"learn":[0.007333867934],"iteration":580,"passed_time":33.73607922,"remaining_time":24.32946161},
{"learn":[0.007314266866],"iteration":581,"passed_time":33.80436535,"remaining_time":24.27873663},
{"learn":[0.007300048568],"iteration":582,"passed_time":33.86559995,"remaining_time":24.22290768},
{"learn":[0.00728721048],"iteration":583,"passed_time":33.92924221,"remaining_time":24.16877528},
{"learn":[0.00726713514],"iteration":584,"passed_time":33.99473482,"remaining_time":24.11592299},
{"learn":[0.007250371051],"iteration":585,"passed_time":34.05883713,"remaining_time":24.06204535},
{"learn":[0.007234388087],"iteration":586,"passed_time":34.12201158,"remaining_time":24.00748004},
{"learn":[0.007223958476],"iteration":587,"passed_time":34.18401717,"remaining_time":23.95206645},
{"learn":[0.007208719958],"iteration":588,"passed_time":34.25183149,"remaining_time":23.90068377},
{"learn":[0.007193568941],"iteration":589,"passed_time":34.31595351,"remaining_time":23.84667956},
{"learn":[0.007183980265],"iteration":590,"passed_time":34.37807379,"remaining_time":23.7912558},
{"learn":[0.007176430326],"iteration":591,"passed_time":34.43778942,"remaining_time":23.73415216},
{"learn":[0.007162733814],"iteration":592,"passed_time":34.49670462,"remaining_time":23.67649036},
{"learn":[0.007148680978],"iteration":593,"passed_time":34.56185626,"remaining_time":23.62308694},
{"learn":[0.007138767087],"iteration":594,"passed_time":34.62442488,"remaining_time":23.56788584},
{"learn":[0.007128948826],"iteration":595,"passed_time":34.68849985,"remaining_time":23.51368111},
{"learn":[0.007112985536],"iteration":596,"passed_time":34.74976498,"remaining_time":23.45754655},
{"learn":[0.007101083547],"iteration":597,"passed_time":34.81362073,"remaining_time":23.40313634},
{"learn":[0.007077379266],"iteration":598,"passed_time":34.87309568,"remaining_time":23.34576189},
{"learn":[0.00706412516],"iteration":599,"passed_time":34.93247137,"remaining_time":23.28831424},
{"learn":[0.007046034119],"iteration":600,"passed_time":34.99390189,"remaining_time":23.23222438},
{"learn":[0.007037136158],"iteration":601,"passed_time":35.05334616,"remaining_time":23.17480361},
{"learn":[0.007029216226],"iteration":602,"passed_time":35.11499033,"remaining_time":23.11882448},
{"learn":[0.007013795263],"iteration":603,"passed_time":35.17780208,"remaining_time":23.0635921},
{"learn":[0.006996543994],"iteration":604,"passed_time":35.23747539,"remaining_time":23.00628558},
{"learn":[0.006985793158],"iteration":605,"passed_time":35.29564253,"remaining_time":22.94799201},
{"learn":[0.006977497397],"iteration":606,"passed_time":35.35618012,"remaining_time":22.89123359},
{"learn":[0.006970632521],"iteration":607,"passed_time":35.42015361,"remaining_time":22.83667798},
{"learn":[0.006960031942],"iteration":608,"passed_time":35.48029888,"remaining_time":22.7796336},
{"learn":[0.006949683852],"iteration":609,"passed_time":35.54007695,"remaining_time":22.72234428},
{"learn":[0.006935283302],"iteration":610,"passed_time":35.60196073,"remaining_time":22.66638744},
{"learn":[0.00692285077],"iteration":611,"passed_time":35.66107943,"remaining_time":22.6086582},
{"learn":[0.006908446562],"iteration":612,"passed_time":35.71852009,"remaining_time":22.54986505},
{"learn":[0.006896169636],"iteration":613,"passed_time":35.77651899,"remaining_time":22.49142725},
{"learn":[0.006887354432],"iteration":614,"passed_time":35.8364187,"remaining_time":22.43418081},
{"learn":[0.006875348496],"iteration":615,"passed_time":35.89441537,"remaining_time":22.37573945},
{"learn":[0.00686427522],"iteration":616,"passed_time":35.9551139,"remaining_time":22.3189767},
{"learn":[0.006854169828],"iteration":617,"passed_time":36.01395005,"remaining_time":22.26105003},
{"learn":[0.006843911026],"iteration":618,"passed_time":36.0747821,"remaining_time":22.20434892},
{"learn":[0.006835299117],"iteration":619,"passed_time":36.13822153,"remaining_time":22.14923255},
{"learn":[0.006817352455],"iteration":620,"passed_time":36.19842486,"remaining_time":22.09211437},
{"learn":[0.006801403552],"iteration":621,"passed_time":36.25826753,"remaining_time":22.03476709},
{"learn":[0.006786201713],"iteration":622,"passed_time":36.31924083,"remaining_time":21.97809598},
{"learn":[0.006775093517],"iteration":623,"passed_time":36.38002104,"remaining_time":21.92129473},
{"learn":[0.006767113328],"iteration":624,"passed_time":36.44164959,"remaining_time":21.86498976},
{"learn":[0.006755645417],"iteration":625,"passed_time":36.50514408,"remaining_time":21.80978256},
{"learn":[0.006738398361],"iteration":626,"passed_time":36.5659453,"remaining_time":21.75294673},
{"learn":[0.006727718166],"iteration":627,"passed_time":36.6265889,"remaining_time":21.69600489},
{"learn":[0.006716311251],"iteration":628,"passed_time":36.68785459,"remaining_time":21.63941821},
{"learn":[0.006712060194],"iteration":629,"passed_time":36.74732864,"remaining_time":21.58176444},
{"learn":[0.006703447929],"iteration":630,"passed_time":36.80778201,"remaining_time":21.52467759},
{"learn":[0.006691459936],"iteration":631,"passed_time":36.86829814,"remaining_time":21.46761664},
{"learn":[0.006684767714],"iteration":632,"passed_time":36.92705278,"remaining_time":21.40952349},
{"learn":[0.00667581888],"iteration":633,"passed_time":36.98897167,"remaining_time":21.35325494},
{"learn":[0.006664224391],"iteration":634,"passed_time":37.05025911,"remaining_time":21.29660563},
{"learn":[0.006651968125],"iteration":635,"passed_time":37.11011832,"remaining_time":21.23912432},
{"learn":[0.006644126443],"iteration":636,"passed_time":37.16854979,"remaining_time":21.18082194},
{"learn":[0.006634325823],"iteration":637,"passed_time":37.227406,"remaining_time":21.12276014},
{"learn":[0.006625670652],"iteration":638,"passed_time":37.29004216,"remaining_time":21.06683133},
{"learn":[0.006609106186],"iteration":639,"passed_time":37.35148972,"remaining_time":21.01021297},
{"learn":[0.006601880465],"iteration":640,"passed_time":37.4090132,"remaining_time":20.95138181},
{"learn":[0.006590074434],"iteration":641,"passed_time":37.46435471,"remaining_time":20.89133799},
{"learn":[0.00657196044],"iteration":642,"passed_time":37.52047666,"remaining_time":20.83174209},
{"learn":[0.006563025088],"iteration":643,"passed_time":37.5794051,"remaining_time":20.77370841},
{"learn":[0.006547941499],"iteration":644,"passed_time":37.64159152,"remaining_time":20.7174651},
{"learn":[0.006536441248],"iteration":645,"passed_time":37.69938156,"remaining_time":20.65879423},
{"learn":[0.00652872515],"iteration":646,"passed_time":37.75537202,"remaining_time":20.59914424},
{"learn":[0.006519783897],"iteration":647,"passed_time":37.8150223,"remaining_time":20.5414936},
{"learn":[0.006506644545],"iteration":648,"passed_time":37.87721349,"remaining_time":20.48521099},
{"learn":[0.00648441692],"iteration":649,"passed_time":37.94605108,"remaining_time":20.43248904},
{"learn":[0.006476507633],"iteration":650,"passed_time":38.01137331,"remaining_time":20.377833},
{"learn":[0.006467688438],"iteration":651,"passed_time":38.07555025,"remaining_time":20.32253296},
{"learn":[0.006456409579],"iteration":652,"passed_time":38.13808537,"remaining_time":20.26633327},
{"learn":[0.006448089356],"iteration":653,"passed_time":38.2004097,"remaining_time":20.21000269},
{"learn":[0.006439042252],"iteration":654,"passed_time":38.2614648,"remaining_time":20.15298528},
{"learn":[0.006430006159],"iteration":655,"passed_time":38.32055476,"remaining_time":20.09492506},
{"learn":[0.006419394983],"iteration":656,"passed_time":38.37666308,"remaining_time":20.03530508},
{"learn":[0.006410114813],"iteration":657,"passed_time":38.43752851,"remaining_time":19.97816831},
{"learn":[0.006400942385],"iteration":658,"passed_time":38.49913827,"remaining_time":19.92140539},
{"learn":[0.006390091133],"iteration":659,"passed_time":38.55861877,"remaining_time":19.86353088},
{"learn":[0.006381223943],"iteration":660,"passed_time":38.61967175,"remaining_time":19.80645798},
{"learn":[0.00637087162],"iteration":661,"passed_time":38.67980807,"remaining_time":19.74890502},
{"learn":[0.006354921729],"iteration":662,"passed_time":38.74007781,"remaining_time":19.6914121},
{"learn":[0.006344441353],"iteration":663,"passed_time":38.79919656,"remaining_time":19.63332838},
{"learn":[0.006335423873],"iteration":664,"passed_time":38.85855795,"remaining_time":19.57536378},
{"learn":[0.006327938701],"iteration":665,"passed_time":38.92297899,"remaining_time":19.51993241},
{"learn":[0.00631265196],"iteration":666,"passed_time":38.98260419,"remaining_time":19.46207975},
{"learn":[0.006301436209],"iteration":667,"passed_time":39.04589794,"remaining_time":19.40604508},
{"learn":[0.006288948944],"iteration":668,"passed_time":39.10411817,"remaining_time":19.3474785},
{"learn":[0.00627950768],"iteration":669,"passed_time":39.16401056,"remaining_time":19.28973654},
{"learn":[0.006272508463],"iteration":670,"passed_time":39.22410673,"remaining_time":19.2320881},
{"learn":[0.006261711251],"iteration":671,"passed_time":39.28491203,"remaining_time":19.17477849},
{"learn":[0.006252987546],"iteration":672,"passed_time":39.34667803,"remaining_time":19.11792528},
{"learn":[0.006244960339],"iteration":673,"passed_time":39.40959996,"remaining_time":19.0616166},
{"learn":[0.00623276255],"iteration":674,"passed_time":39.47192027,"remaining_time":19.00499865},
{"learn":[0.006225247979],"iteration":675,"passed_time":39.53465676,"remaining_time":18.9485633},
{"learn":[0.006216287995],"iteration":676,"passed_time":39.59342986,"remaining_time":18.89021838},
{"learn":[0.006207900347],"iteration":677,"passed_time":39.65121723,"remaining_time":18.83140405},
{"learn":[0.006198368479],"iteration":678,"passed_time":39.71303908,"remaining_time":18.77450007},
{"learn":[0.006191655153],"iteration":679,"passed_time":39.77385713,"remaining_time":18.71710924},
{"learn":[0.006177411614],"iteration":680,"passed_time":39.83419852,"remaining_time":18.65948506},
{"learn":[0.006167448133],"iteration":681,"passed_time":39.89312132,"remaining_time":18.60119147},
{"learn":[0.00615956306],"iteration":682,"passed_time":39.95182668,"remaining_time":18.54279511},
{"learn":[0.006145504715],"iteration":683,"passed_time":40.01223383,"remaining_time":18.48518405},
{"learn":[0.006136645343],"iteration":684,"passed_time":40.07207872,"remaining_time":18.42730627},
{"learn":[0.006122982301],"iteration":685,"passed_time":40.13141467,"remaining_time":18.3691898},
{"learn":[0.006117189879],"iteration":686,"passed_time":40.19060153,"remaining_time":18.31100186},
{"learn":[0.006107925363],"iteration":687,"passed_time":40.25015852,"remaining_time":18.25297886},
{"learn":[0.006099187548],"iteration":688,"passed_time":40.30992691,"remaining_time":18.19504683},
{"learn":[0.006088092545],"iteration":689,"passed_time":40.36701406,"remaining_time":18.13590487},
{"learn":[0.006083080854],"iteration":690,"passed_time":40.42358113,"remaining_time":18.07653628},
{"learn":[0.006070689712],"iteration":691,"passed_time":40.48133525,"remaining_time":18.01770413},
{"learn":[0.006065118101],"iteration":692,"passed_time":40.53787698,"remaining_time":17.958338},
{"learn":[0.006053648641],"iteration":693,"passed_time":40.59499691,"remaining_time":17.89923495},
{"learn":[0.006038316898],"iteration":694,"passed_time":40.65112957,"remaining_time":17.83970434},
{"learn":[0.006027860814],"iteration":695,"passed_time":40.70964364,"remaining_time":17.78122366},
{"learn":[0.006019713164],"iteration":696,"passed_time":40.76838389,"remaining_time":17.7228412},
{"learn":[0.006008837309],"iteration":697,"passed_time":40.82902475,"remaining_time":17.66528005},
{"learn":[0.005996675589],"iteration":698,"passed_time":40.8900078,"remaining_time":17.60785743},
{"learn":[0.0059850302],"iteration":699,"passed_time":40.94547019,"remaining_time":17.54805865},
{"learn":[0.00597567529],"iteration":700,"passed_time":41.00157298,"remaining_time":17.48854539},
{"learn":[0.00596518577],"iteration":701,"passed_time":41.05713599,"remaining_time":17.42881271},
{"learn":[0.005956121753],"iteration":702,"passed_time":41.11222521,"remaining_time":17.36889173},
{"learn":[0.005945367798],"iteration":703,"passed_time":41.16714802,"remaining_time":17.30891451},
{"learn":[0.005927526243],"iteration":704,"passed_time":41.22144424,"remaining_time":17.24868943},
{"learn":[0.005920725114],"iteration":705,"passed_time":41.27523371,"remaining_time":17.18827013},
{"learn":[0.005913628874],"iteration":706,"passed_time":41.32862365,"remaining_time":17.127704},
{"learn":[0.005901689924],"iteration":707,"passed_time":41.38323248,"remaining_time":17.06766085},
{"learn":[0.005893344173],"iteration":708,"passed_time":41.43748867,"remaining_time":17.0074883},
{"learn":[0.00588227879],"iteration":709,"passed_time":41.49484273,"remaining_time":16.94859773},
{"learn":[0.005876586384],"iteration":710,"passed_time":41.5526555,"remaining_time":16.88989795},
{"learn":[0.005867468588],"iteration":711,"passed_time":41.60671662,"remaining_time":16.82968313},
{"learn":[0.005860954525],"iteration":712,"passed_time":41.6614743,"remaining_time":16.76976595},
{"learn":[0.005851666317],"iteration":713,"passed_time":41.71562327,"remaining_time":16.7096194},
{"learn":[0.00584535641],"iteration":714,"passed_time":41.76917471,"remaining_time":16.64925146},
{"learn":[0.005837379297],"iteration":715,"passed_time":41.82402821,"remaining_time":16.58941901},
{"learn":[0.005830454879],"iteration":716,"passed_time":41.87964523,"remaining_time":16.52990181},
{"learn":[0.005822201346],"iteration":717,"passed_time":41.93484047,"remaining_time":16.47022982},
{"learn":[0.005812472607],"iteration":718,"passed_time":41.99277527,"remaining_time":16.41164096},
{"learn":[0.00580471956],"iteration":719,"passed_time":42.04783261,"remaining_time":16.3519349},
{"learn":[0.005797148812],"iteration":720,"passed_time":42.10502918,"remaining_time":16.29306954},
{"learn":[0.005783729784],"iteration":721,"passed_time":42.16070889,"remaining_time":16.23362475},
{"learn":[0.005773151944],"iteration":722,"passed_time":42.21471057,"remaining_time":16.17354748},
{"learn":[0.005764201952],"iteration":723,"passed_time":42.26671984,"remaining_time":16.11272745},
{"learn":[0.005748508221],"iteration":724,"passed_time":42.3187584,"remaining_time":16.05194284},
{"learn":[0.005742117755],"iteration":725,"passed_time":42.37183845,"remaining_time":15.99157539},
{"learn":[0.005734768287],"iteration":726,"passed_time":42.42464673,"remaining_time":15.93112594},
{"learn":[0.005723902306],"iteration":727,"passed_time":42.47705532,"remaining_time":15.87054814},
{"learn":[0.005713631629],"iteration":728,"passed_time":42.53343086,"remaining_time":15.81146744},
{"learn":[0.005706407665],"iteration":729,"passed_time":42.59056669,"remaining_time":15.75267535},
{"learn":[0.00569750851],"iteration":730,"passed_time":42.64703247,"remaining_time":15.69364122},
{"learn":[0.0056924344],"iteration":731,"passed_time":42.70235561,"remaining_time":15.63419577},
{"learn":[0.005685848932],"iteration":732,"passed_time":42.75762014,"remaining_time":15.57474021},
{"learn":[0.005677371127],"iteration":733,"passed_time":42.81441217,"remaining_time":15.51584964},
{"learn":[0.005658332647],"iteration":734,"passed_time":42.86884354,"remaining_time":15.45611366},
{"learn":[0.00565339279],"iteration":735,"passed_time":42.92558212,"remaining_time":15.39721967},
{"learn":[0.005645855209],"iteration":736,"passed_time":42.98274755,"remaining_time":15.33848386},
{"learn":[0.005638550581],"iteration":737,"passed_time":43.04296432,"remaining_time":15.28083557},
{"learn":[0.005629393855],"iteration":738,"passed_time":43.10227585,"remaining_time":15.22286062},
{"learn":[0.005621233405],"iteration":739,"passed_time":43.15566851,"remaining_time":15.16280245},
{"learn":[0.005610562557],"iteration":740,"passed_time":43.21129673,"remaining_time":15.10354366},
{"learn":[0.005604137767],"iteration":741,"passed_time":43.27056354,"remaining_time":15.04555983},
{"learn":[0.005591776565],"iteration":742,"passed_time":43.32983616,"remaining_time":14.98757455},
{"learn":[0.005574294078],"iteration":743,"passed_time":43.3859705,"remaining_time":14.92850598},
{"learn":[0.005567986693],"iteration":744,"passed_time":43.44735126,"remaining_time":14.87124104},
{"learn":[0.005560743816],"iteration":745,"passed_time":43.50347988,"remaining_time":14.8121768},
{"learn":[0.005551055966],"iteration":746,"passed_time":43.56087301,"remaining_time":14.75354869},
{"learn":[0.005542805537],"iteration":747,"passed_time":43.62016946,"remaining_time":14.69556511},
{"learn":[0.005532412697],"iteration":748,"passed_time":43.67894851,"remaining_time":14.63740464},
{"learn":[0.005517701072],"iteration":749,"passed_time":43.73522256,"remaining_time":14.57840752},
{"learn":[0.005509582247],"iteration":750,"passed_time":43.79095034,"remaining_time":14.51923653},
{"learn":[0.005502277233],"iteration":751,"passed_time":43.84747834,"remaining_time":14.4603386},
{"learn":[0.005496273098],"iteration":752,"passed_time":43.90778513,"remaining_time":14.40268649},
{"learn":[0.005489382032],"iteration":753,"passed_time":43.96574606,"remaining_time":14.34426198},
{"learn":[0.00548132657],"iteration":754,"passed_time":44.02580899,"remaining_time":14.2865208},
{"learn":[0.005476195247],"iteration":755,"passed_time":44.08706438,"remaining_time":14.22915835},
{"learn":[0.00546936068],"iteration":756,"passed_time":44.15139604,"remaining_time":14.1727731},
{"learn":[0.005459346645],"iteration":757,"passed_time":44.21090217,"remaining_time":14.11482629},
{"learn":[0.005451025586],"iteration":758,"passed_time":44.26383224,"remaining_time":14.05478731},
{"learn":[0.005445817319],"iteration":759,"passed_time":44.31943107,"remaining_time":13.99560981},
{"learn":[0.0054398059],"iteration":760,"passed_time":44.37383476,"remaining_time":13.93606637},
{"learn":[0.005434901445],"iteration":761,"passed_time":44.42701823,"remaining_time":13.8761553},
{"learn":[0.005428080868],"iteration":762,"passed_time":44.48381353,"remaining_time":13.81738376},
{"learn":[0.005419580984],"iteration":763,"passed_time":44.54008803,"remaining_time":13.75845651},
{"learn":[0.005412337202],"iteration":764,"passed_time":44.59714708,"remaining_time":13.69977721},
{"learn":[0.00540603471],"iteration":765,"passed_time":44.65588505,"remaining_time":13.64161501},
{"learn":[0.005399250981],"iteration":766,"passed_time":44.71506045,"remaining_time":13.58358421},
{"learn":[0.005391797638],"iteration":767,"passed_time":44.77356246,"remaining_time":13.52534699},
{"learn":[0.005381003563],"iteration":768,"passed_time":44.83624804,"remaining_time":13.4683658},
{"learn":[0.005371751669],"iteration":769,"passed_time":44.8938535,"remaining_time":13.40985234},
{"learn":[0.005364830398],"iteration":770,"passed_time":44.95181761,"remaining_time":13.35144777},
{"learn":[0.005355488713],"iteration":771,"passed_time":45.01322237,"remaining_time":13.29406049},
{"learn":[0.005350521774],"iteration":772,"passed_time":45.07172641,"remaining_time":13.23581099},
{"learn":[0.005343464236],"iteration":773,"passed_time":45.12729566,"remaining_time":13.1767039},
{"learn":[0.005337329614],"iteration":774,"passed_time":45.18861477,"remaining_time":13.11927526},
{"learn":[0.005323524916],"iteration":775,"passed_time":45.24629304,"remaining_time":13.06078562},
{"learn":[0.00531739044],"iteration":776,"passed_time":45.3005916,"remaining_time":13.00132809},
{"learn":[0.00530971207],"iteration":777,"passed_time":45.35954242,"remaining_time":12.94321133},
{"learn":[0.005303848859],"iteration":778,"passed_time":45.41684962,"remaining_time":12.88462614},
{"learn":[0.005296869529],"iteration":779,"passed_time":45.4737592,"remaining_time":12.82593208},
{"learn":[0.005290406945],"iteration":780,"passed_time":45.53206869,"remaining_time":12.76763514},
{"learn":[0.005282221495],"iteration":781,"passed_time":45.59131864,"remaining_time":12.70960034},
{"learn":[0.005274699329],"iteration":782,"passed_time":45.64828468,"remaining_time":12.65092947},
{"learn":[0.005260118932],"iteration":783,"passed_time":45.70884575,"remaining_time":12.59325342},
{"learn":[0.005252679778],"iteration":784,"passed_time":45.76817983,"remaining_time":12.53523397},
{"learn":[0.005245462629],"iteration":785,"passed_time":45.82797277,"remaining_time":12.4773361},
{"learn":[0.005233143225],"iteration":786,"passed_time":45.88652373,"remaining_time":12.41909727},
{"learn":[0.00522855738],"iteration":787,"passed_time":45.94881958,"remaining_time":12.36186517},
{"learn":[0.005225369875],"iteration":788,"passed_time":46.0080488,"remaining_time":12.30380012},
{"learn":[0.005219266986],"iteration":789,"passed_time":46.07087485,"remaining_time":12.24668825},
{"learn":[0.005213047074],"iteration":790,"passed_time":46.13720977,"remaining_time":12.19048905},
{"learn":[0.005206631947],"iteration":791,"passed_time":46.20078121,"remaining_time":12.1335385},
{"learn":[0.005200770032],"iteration":792,"passed_time":46.26747522,"remaining_time":12.07738634},
{"learn":[0.005194956401],"iteration":793,"passed_time":46.32999403,"remaining_time":12.0201244},
{"learn":[0.005189784893],"iteration":794,"passed_time":46.39369068,"remaining_time":11.96315294},
{"learn":[0.005185339061],"iteration":795,"passed_time":46.45474981,"remaining_time":11.90548865},
{"learn":[0.005178220229],"iteration":796,"passed_time":46.51839643,"remaining_time":11.84847487},
{"learn":[0.005172033105],"iteration":797,"passed_time":46.58022039,"remaining_time":11.79098311},
{"learn":[0.005167884358],"iteration":798,"passed_time":46.64357868,"remaining_time":11.73386648},
{"learn":[0.005160866382],"iteration":799,"passed_time":46.70373182,"remaining_time":11.67593296},
{"learn":[0.005157155245],"iteration":800,"passed_time":46.7634398,"remaining_time":11.6178833},
{"learn":[0.005148114962],"iteration":801,"passed_time":46.8254032,"remaining_time":11.56038633},
{"learn":[0.005139156838],"iteration":802,"passed_time":46.88751581,"remaining_time":11.50291484},
{"learn":[0.005134316801],"iteration":803,"passed_time":46.94783677,"remaining_time":11.44499503},
{"learn":[0.005126921804],"iteration":804,"passed_time":47.01168657,"remaining_time":11.38792408},
{"learn":[0.0051197041],"iteration":805,"passed_time":47.07256985,"remaining_time":11.33012227},
{"learn":[0.005114885078],"iteration":806,"passed_time":47.13874053,"remaining_time":11.27357735},
{"learn":[0.005106820389],"iteration":807,"passed_time":47.19969954,"remaining_time":11.21577019},
{"learn":[0.005102228178],"iteration":808,"passed_time":47.26177299,"remaining_time":11.15821834},
{"learn":[0.005096446693],"iteration":809,"passed_time":47.32264917,"remaining_time":11.1003745},
{"learn":[0.005089540181],"iteration":810,"passed_time":47.38555673,"remaining_time":11.04299657},
{"learn":[0.005084812518],"iteration":811,"passed_time":47.44781662,"remaining_time":10.98545508},
{"learn":[0.005077958662],"iteration":812,"passed_time":47.50916341,"remaining_time":10.92769195},
{"learn":[0.005072859495],"iteration":813,"passed_time":47.56883776,"remaining_time":10.86953787},
{"learn":[0.005067725111],"iteration":814,"passed_time":47.62783684,"remaining_time":10.81122677},
{"learn":[0.00506292648],"iteration":815,"passed_time":47.68832957,"remaining_time":10.75325079},
{"learn":[0.005057770944],"iteration":816,"passed_time":47.74608051,"remaining_time":10.69465451},
{"learn":[0.005054863669],"iteration":817,"passed_time":47.80527197,"remaining_time":10.6363808},
{"learn":[0.005046682921],"iteration":818,"passed_time":47.86551001,"remaining_time":10.57833616},
{"learn":[0.005036386649],"iteration":819,"passed_time":47.92624853,"remaining_time":10.52039602},
{"learn":[0.005030485099],"iteration":820,"passed_time":47.98600121,"remaining_time":10.46223412},
{"learn":[0.005020937002],"iteration":821,"passed_time":48.04741624,"remaining_time":10.40442833},
{"learn":[0.005015557156],"iteration":822,"passed_time":48.10274014,"remaining_time":10.34530377},
{"learn":[0.00500426354],"iteration":823,"passed_time":48.15982565,"remaining_time":10.2865647},
{"learn":[0.00500107728],"iteration":824,"passed_time":48.22099814,"remaining_time":10.22869657},
{"learn":[0.004996052873],"iteration":825,"passed_time":48.28172376,"remaining_time":10.17072631},
{"learn":[0.004986555431],"iteration":826,"passed_time":48.34245505,"remaining_time":10.11275057},
{"learn":[0.004977176761],"iteration":827,"passed_time":48.40537377,"remaining_time":10.05522257},
{"learn":[0.004971969274],"iteration":828,"passed_time":48.46453696,"remaining_time":9.9969069},
{"learn":[0.004966485399],"iteration":829,"passed_time":48.52265186,"remaining_time":9.938374478},
{"learn":[0.004960861359],"iteration":830,"passed_time":48.57790102,"remaining_time":9.879260256},
{"learn":[0.004956133795],"iteration":831,"passed_time":48.63372455,"remaining_time":9.820271302},
{"learn":[0.004951871504],"iteration":832,"passed_time":48.68920736,"remaining_time":9.761221643},
{"learn":[0.004945338662],"iteration":833,"passed_time":48.74209119,"remaining_time":9.701663235},
{"learn":[0.004939867617],"iteration":834,"passed_time":48.79715463,"remaining_time":9.642551514},
{"learn":[0.004937165589],"iteration":835,"passed_time":48.85463574,"remaining_time":9.583923757},
{"learn":[0.004930310687],"iteration":836,"passed_time":48.91000696,"remaining_time":9.524887855},
{"learn":[0.004921997545],"iteration":837,"passed_time":48.97047343,"remaining_time":9.466845699},
{"learn":[0.00491469487],"iteration":838,"passed_time":49.03638513,"remaining_time":9.409842677},
{"learn":[0.004906707644],"iteration":839,"passed_time":49.09895702,"remaining_time":9.35218229},
{"learn":[0.004902919846],"iteration":840,"passed_time":49.15655868,"remaining_time":9.293570548},
{"learn":[0.004898792911],"iteration":841,"passed_time":49.21930525,"remaining_time":9.235926638},
{"learn":[0.00489356159],"iteration":842,"passed_time":49.27788556,"remaining_time":9.177494702},
{"learn":[0.00488720586],"iteration":843,"passed_time":49.33628338,"remaining_time":9.119028681},
{"learn":[0.004882668986],"iteration":844,"passed_time":49.39112835,"remaining_time":9.059911118},
{"learn":[0.004878592221],"iteration":845,"passed_time":49.44663863,"remaining_time":9.000924763},
{"learn":[0.004874194085],"iteration":846,"passed_time":49.50868881,"remaining_time":8.943127967},
{"learn":[0.004869812438],"iteration":847,"passed_time":49.57217597,"remaining_time":8.885578712},
{"learn":[0.004862844741],"iteration":848,"passed_time":49.63066701,"remaining_time":8.827126877},
{"learn":[0.004859039512],"iteration":849,"passed_time":49.69008213,"remaining_time":8.768838023},
{"learn":[0.004853134868],"iteration":850,"passed_time":49.74900056,"remaining_time":8.710459558},
{"learn":[0.00484885218],"iteration":851,"passed_time":49.80985138,"remaining_time":8.652415497},
{"learn":[0.004844660367],"iteration":852,"passed_time":49.87456686,"remaining_time":8.595030866},
{"learn":[0.004836750984],"iteration":853,"passed_time":49.93526684,"remaining_time":8.536942575},
{"learn":[0.004824260632],"iteration":854,"passed_time":49.99446812,"remaining_time":8.478594008},
{"learn":[0.004820185384],"iteration":855,"passed_time":50.05631996,"remaining_time":8.420689339},
{"learn":[0.004815382661],"iteration":856,"passed_time":50.11686362,"remaining_time":8.362557173},
{"learn":[0.004807671882],"iteration":857,"passed_time":50.1783303,"remaining_time":8.304572147},
{"learn":[0.004795893494],"iteration":858,"passed_time":50.24508248,"remaining_time":8.2474466},
{"learn":[0.004791109171],"iteration":859,"passed_time":50.30710809,"remaining_time":8.189529224},
{"learn":[0.004787521385],"iteration":860,"passed_time":50.36779622,"remaining_time":8.131386382},
{"learn":[0.004782037184],"iteration":861,"passed_time":50.42889585,"remaining_time":8.073303512},
{"learn":[0.004776101481],"iteration":862,"passed_time":50.48930152,"remaining_time":8.015103486},
{"learn":[0.004768648526],"iteration":863,"passed_time":50.55164996,"remaining_time":7.95720416},
{"learn":[0.004759842639],"iteration":864,"passed_time":50.61571261,"remaining_time":7.899562084},
{"learn":[0.004752772586],"iteration":865,"passed_time":50.68149873,"remaining_time":7.84217186},
{"learn":[0.004748140457],"iteration":866,"passed_time":50.74355596,"remaining_time":7.784190246},
{"learn":[0.004742299401],"iteration":867,"passed_time":50.80594105,"remaining_time":7.7262491},
{"learn":[0.004737325358],"iteration":868,"passed_time":50.86539412,"remaining_time":7.667855731},
{"learn":[0.004730069292],"iteration":869,"passed_time":50.92556472,"remaining_time":7.609567142},
{"learn":[0.004724469892],"iteration":870,"passed_time":50.98644214,"remaining_time":7.551378916},
{"learn":[0.004717536365],"iteration":871,"passed_time":51.04840178,"remaining_time":7.49334338},
{"learn":[0.004711706027],"iteration":872,"passed_time":51.11206049,"remaining_time":7.435546028},
{"learn":[0.004700739951],"iteration":873,"passed_time":51.17225037,"remaining_time":7.37723518},
{"learn":[0.004695660224],"iteration":874,"passed_time":51.23004683,"remaining_time":7.318578119},
{"learn":[0.004690892264],"iteration":875,"passed_time":51.28499764,"remaining_time":7.259520214},
{"learn":[0.004685772266],"iteration":876,"passed_time":51.3408514,"remaining_time":7.200598315},
{"learn":[0.004678923348],"iteration":877,"passed_time":51.40023118,"remaining_time":7.142173353},
{"learn":[0.004672287761],"iteration":878,"passed_time":51.4593973,"remaining_time":7.083716806},
{"learn":[0.004668057874],"iteration":879,"passed_time":51.51817312,"remaining_time":7.025205426},
{"learn":[0.00466329153],"iteration":880,"passed_time":51.57731052,"remaining_time":6.966742284},
{"learn":[0.004655530333],"iteration":881,"passed_time":51.64025183,"remaining_time":6.908786526},
{"learn":[0.004648557611],"iteration":882,"passed_time":51.70253043,"remaining_time":6.850731666},
{"learn":[0.004642543807],"iteration":883,"passed_time":51.76708022,"remaining_time":6.792965278},
{"learn":[0.004635344036],"iteration":884,"passed_time":51.82795086,"remaining_time":6.734705479},
{"learn":[0.004625502321],"iteration":885,"passed_time":51.89135744,"remaining_time":6.676766082},
{"learn":[0.004618037357],"iteration":886,"passed_time":51.95354322,"remaining_time":6.618658832},
{"learn":[0.004612324568],"iteration":887,"passed_time":52.01554769,"remaining_time":6.560519529},
{"learn":[0.00460649804],"iteration":888,"passed_time":52.07500107,"remaining_time":6.502053001},
{"learn":[0.004601846459],"iteration":889,"passed_time":52.13591157,"remaining_time":6.443764352},
{"learn":[0.004596298255],"iteration":890,"passed_time":52.19617336,"remaining_time":6.385390456},
{"learn":[0.004591979408],"iteration":891,"passed_time":52.25444169,"remaining_time":6.326770967},
{"learn":[0.004586908696],"iteration":892,"passed_time":52.31224764,"remaining_time":6.268096862},
{"learn":[0.004572883981],"iteration":893,"passed_time":52.36968187,"remaining_time":6.209380624},
{"learn":[0.004566970282],"iteration":894,"passed_time":52.43226778,"remaining_time":6.151271639},
{"learn":[0.00456373],"iteration":895,"passed_time":52.49279735,"remaining_time":6.092913979},
{"learn":[0.004559602297],"iteration":896,"passed_time":52.55281721,"remaining_time":6.034492946},
{"learn":[0.004555223368],"iteration":897,"passed_time":52.61429816,"remaining_time":5.976234312},
{"learn":[0.004546180107],"iteration":898,"passed_time":52.67319829,"remaining_time":5.917678562},
{"learn":[0.00454044482],"iteration":899,"passed_time":52.73391441,"remaining_time":5.859323823},
{"learn":[0.004537117458],"iteration":900,"passed_time":52.79713604,"remaining_time":5.801239143},
{"learn":[0.004532957397],"iteration":901,"passed_time":52.85912219,"remaining_time":5.743008841},
{"learn":[0.004527699656],"iteration":902,"passed_time":52.91920623,"remaining_time":5.684565896},
{"learn":[0.004522695198],"iteration":903,"passed_time":52.98214492,"remaining_time":5.626422469},
{"learn":[0.004516636166],"iteration":904,"passed_time":53.04336154,"remaining_time":5.568087675},
{"learn":[0.004508089194],"iteration":905,"passed_time":53.10610847,"remaining_time":5.509905294},
{"learn":[0.004501773071],"iteration":906,"passed_time":53.16512877,"remaining_time":5.451330734},
{"learn":[0.004497638905],"iteration":907,"passed_time":53.22479212,"remaining_time":5.392820347},
{"learn":[0.004492751922],"iteration":908,"passed_time":53.28543583,"remaining_time":5.334405567},
{"learn":[0.004485742145],"iteration":909,"passed_time":53.34813882,"remaining_time":5.276189554},
{"learn":[0.004481544945],"iteration":910,"passed_time":53.41070396,"remaining_time":5.217950222},
{"learn":[0.004476803487],"iteration":911,"passed_time":53.47328636,"remaining_time":5.15970307},
{"learn":[0.004468235106],"iteration":912,"passed_time":53.5329808,"remaining_time":5.101171226},
{"learn":[0.004463245488],"iteration":913,"passed_time":53.59111245,"remaining_time":5.042489793},
{"learn":[0.004457036726],"iteration":914,"passed_time":53.65042605,"remaining_time":4.98391936},
{"learn":[0.004450387876],"iteration":915,"passed_time":53.7079263,"remaining_time":4.925181014},
{"learn":[0.00444659213],"iteration":916,"passed_time":53.76713828,"remaining_time":4.866600302},
{"learn":[0.004442467476],"iteration":917,"passed_time":53.82705888,"remaining_time":4.808081512},
{"learn":[0.004436443773],"iteration":918,"passed_time":53.89013315,"remaining_time":4.749837633},
{"learn":[0.004432237938],"iteration":919,"passed_time":53.95193215,"remaining_time":4.691472361},
{"learn":[0.004427835191],"iteration":920,"passed_time":54.01330105,"remaining_time":4.63306274},
{"learn":[0.004421703212],"iteration":921,"passed_time":54.0721727,"remaining_time":4.574435435},
{"learn":[0.004417612252],"iteration":922,"passed_time":54.13176844,"remaining_time":4.515868006},
{"learn":[0.004413308262],"iteration":923,"passed_time":54.19447653,"remaining_time":4.457554347},
{"learn":[0.004409372097],"iteration":924,"passed_time":54.25513219,"remaining_time":4.399064772},
{"learn":[0.004405228086],"iteration":925,"passed_time":54.31948444,"remaining_time":4.340865927},
{"learn":[0.004397026694],"iteration":926,"passed_time":54.37637818,"remaining_time":4.282066458},
{"learn":[0.004389607198],"iteration":927,"passed_time":54.43450245,"remaining_time":4.223366569},
{"learn":[0.004385102657],"iteration":928,"passed_time":54.49151408,"remaining_time":4.164582885},
{"learn":[0.004380865782],"iteration":929,"passed_time":54.5498319,"remaining_time":4.105901326},
{"learn":[0.004376908791],"iteration":930,"passed_time":54.60676928,"remaining_time":4.047118238},
{"learn":[0.004373663701],"iteration":931,"passed_time":54.66662324,"remaining_time":3.98855191},
{"learn":[0.004368112886],"iteration":932,"passed_time":54.72549115,"remaining_time":3.929912012},
{"learn":[0.004365092843],"iteration":933,"passed_time":54.78561412,"remaining_time":3.871360312},
{"learn":[0.004359516574],"iteration":934,"passed_time":54.84358842,"remaining_time":3.812655879},
{"learn":[0.004355701418],"iteration":935,"passed_time":54.90219893,"remaining_time":3.753996508},
{"learn":[0.00435051499],"iteration":936,"passed_time":54.96079416,"remaining_time":3.695336213},
{"learn":[0.004345728389],"iteration":937,"passed_time":55.01990945,"remaining_time":3.636710433},
{"learn":[0.00434109698],"iteration":938,"passed_time":55.07843803,"remaining_time":3.578045495},
{"learn":[0.004338435229],"iteration":939,"passed_time":55.13710671,"remaining_time":3.51938979},
{"learn":[0.004332080537],"iteration":940,"passed_time":55.19552172,"remaining_time":3.460718153},
{"learn":[0.004324128451],"iteration":941,"passed_time":55.25268367,"remaining_time":3.401969907},
{"learn":[0.00431787589],"iteration":942,"passed_time":55.30950229,"remaining_time":3.343204274},
{"learn":[0.00431242998],"iteration":943,"passed_time":55.36874166,"remaining_time":3.28458637},
{"learn":[0.004309657985],"iteration":944,"passed_time":55.42588114,"remaining_time":3.225844934},
{"learn":[0.004306263338],"iteration":945,"passed_time":55.48630997,"remaining_time":3.16729465},
{"learn":[0.004300723203],"iteration":946,"passed_time":55.54565198,"remaining_time":3.108679572},
{"learn":[0.00429361987],"iteration":947,"passed_time":55.60320312,"remaining_time":3.049964728},
{"learn":[0.004289796359],"iteration":948,"passed_time":55.66120696,"remaining_time":2.991276665},
{"learn":[0.004286662541],"iteration":949,"passed_time":55.71933231,"remaining_time":2.932596437},
{"learn":[0.004282101136],"iteration":950,"passed_time":55.77705275,"remaining_time":2.873896514},
{"learn":[0.004277181382],"iteration":951,"passed_time":55.83430229,"remaining_time":2.815174905},
{"learn":[0.00427301019],"iteration":952,"passed_time":55.89135218,"remaining_time":2.75644654},
{"learn":[0.004265590651],"iteration":953,"passed_time":55.94854094,"remaining_time":2.697728389},
{"learn":[0.004263301897],"iteration":954,"passed_time":56.0078932,"remaining_time":2.639115386},
{"learn":[0.00425666632],"iteration":955,"passed_time":56.06444925,"remaining_time":2.580372141},
{"learn":[0.004251823364],"iteration":956,"passed_time":56.12026277,"remaining_time":2.521600103},
{"learn":[0.004249050653],"iteration":957,"passed_time":56.17706402,"remaining_time":2.462877546},
{"learn":[0.00424639004],"iteration":958,"passed_time":56.23144661,"remaining_time":2.40405559},
{"learn":[0.004242711114],"iteration":959,"passed_time":56.28923309,"remaining_time":2.345384712},
{"learn":[0.004238329706],"iteration":960,"passed_time":56.34472814,"remaining_time":2.286622682},
{"learn":[0.0042344674],"iteration":961,"passed_time":56.39973231,"remaining_time":2.227848054},
{"learn":[0.004229660714],"iteration":962,"passed_time":56.4556225,"remaining_time":2.169115299},
{"learn":[0.004224994316],"iteration":963,"passed_time":56.51263635,"remaining_time":2.110430403},
{"learn":[0.004220540253],"iteration":964,"passed_time":56.56769542,"remaining_time":2.051678072},
{"learn":[0.004213196817],"iteration":965,"passed_time":56.62814006,"remaining_time":1.993122942},
{"learn":[0.004209691545],"iteration":966,"passed_time":56.68766524,"remaining_time":1.934532526},
{"learn":[0.004203334328],"iteration":967,"passed_time":56.74387692,"remaining_time":1.875830642},
{"learn":[0.004200492614],"iteration":968,"passed_time":56.79575596,"remaining_time":1.816995289},
{"learn":[0.004192858103],"iteration":969,"passed_time":56.84419055,"remaining_time":1.758067749},
{"learn":[0.004181962475],"iteration":970,"passed_time":56.90154276,"remaining_time":1.699428157},
{"learn":[0.004175937909],"iteration":971,"passed_time":56.95547509,"remaining_time":1.640692698},
{"learn":[0.004170643725],"iteration":972,"passed_time":57.01077762,"remaining_time":1.582005134},
{"learn":[0.004163490967],"iteration":973,"passed_time":57.06462899,"remaining_time":1.523285784},
{"learn":[0.00416003554],"iteration":974,"passed_time":57.11767374,"remaining_time":1.464555737},
{"learn":[0.004156178633],"iteration":975,"passed_time":57.1700058,"remaining_time":1.405819815},
{"learn":[0.004152139757],"iteration":976,"passed_time":57.22288186,"remaining_time":1.347109808},
{"learn":[0.004147005699],"iteration":977,"passed_time":57.27648361,"remaining_time":1.288428057},
{"learn":[0.004143787657],"iteration":978,"passed_time":57.32884547,"remaining_time":1.229730087},
{"learn":[0.004138234996],"iteration":979,"passed_time":57.38385723,"remaining_time":1.171099127},
{"learn":[0.004134365603],"iteration":980,"passed_time":57.4363112,"remaining_time":1.112426007},
{"learn":[0.004130046222],"iteration":981,"passed_time":57.48876981,"remaining_time":1.053765638},
{"learn":[0.004124699365],"iteration":982,"passed_time":57.54278136,"remaining_time":0.9951447438},
{"learn":[0.004121090412],"iteration":983,"passed_time":57.59705367,"remaining_time":0.9365374581},
{"learn":[0.00411757742],"iteration":984,"passed_time":57.65213904,"remaining_time":0.877951356},
{"learn":[0.004114079296],"iteration":985,"passed_time":57.70552407,"remaining_time":0.819348212},
{"learn":[0.004105055244],"iteration":986,"passed_time":57.75723002,"remaining_time":0.7607335262},
{"learn":[0.004101251738],"iteration":987,"passed_time":57.8102681,"remaining_time":0.7021490053},
{"learn":[0.004099917264],"iteration":988,"passed_time":57.86580633,"remaining_time":0.6436035082},
{"learn":[0.004096966556],"iteration":989,"passed_time":57.91825277,"remaining_time":0.5850328562},
{"learn":[0.004091765485],"iteration":990,"passed_time":57.97663421,"remaining_time":0.5265284641},
{"learn":[0.004088018432],"iteration":991,"passed_time":58.03159758,"remaining_time":0.4679967547},
{"learn":[0.004083746516],"iteration":992,"passed_time":58.08928085,"remaining_time":0.4094914058},
{"learn":[0.004081325004],"iteration":993,"passed_time":58.14427001,"remaining_time":0.3509714488},
{"learn":[0.004078007503],"iteration":994,"passed_time":58.19786829,"remaining_time":0.2924515994},
{"learn":[0.004071474927],"iteration":995,"passed_time":58.24999299,"remaining_time":0.2339357148},
{"learn":[0.004066846479],"iteration":996,"passed_time":58.305268,"remaining_time":0.1754421304},
{"learn":[0.004063780252],"iteration":997,"passed_time":58.35859104,"remaining_time":0.1169510842},
{"learn":[0.004059962492],"iteration":998,"passed_time":58.41711113,"remaining_time":0.05847558672},
{"learn":[0.00405700217],"iteration":999,"passed_time":58.47621869,"remaining_time":0}
]}